[{"summonerName":"JUGKlNG","gameStartTimestamp":1660070039102,"gameEndTimestamp":1660071522944,"gameId":6066463413,"gameDuration":1483,"gameMode":"CLASSIC","totalKills":22,"participants":[{"summonerName":"타 잔","kills":5,"assists":2,"deaths":6,"champLevel":15,"championName":"Sett","detectorWardsPlaced":3,"wardsPlaced":10,"wardsKilled":3,"doubleKills":0,"tripleKills":0,"quadreKills":0,"pentaKills":0,"goldEarned":10432,"individualPosition":"TOP","item0":6631,"item1":3111,"item2":3044,"item3":1055,"item4":3153,"item5":0,"item6":3364,"totalDamageDealt":114550,"summoner1Id":14,"summoner2Id":4,"perks":{"statPerks":{"defense":5002,"flex":5008,"offense":5005},"styles":[{"description":"primaryStyle","selections":[{"perk":8010,"var1":467,"var2":0,"var3":0},{"perk":9111,"var1":455,"var2":140,"var3":0},{"perk":9104,"var1":22,"var2":10,"var3":0},{"perk":8299,"var1":788,"var2":0,"var3":0}],"style":8000},{"description":"subStyle","selections":[{"perk":8473,"var1":424,"var2":0,"var3":0},{"perk":8446,"var1":1417,"var2":0,"var3":0}],"style":8400}]},"totalMinionsKilled":165,"win":false},{"summonerName":"NS Sylvie","kills":10,"assists":4,"deaths":6,"champLevel":14,"championName":"MonkeyKing","detectorWardsPlaced":3,"wardsPlaced":4,"wardsKilled":5,"doubleKills":0,"tripleKills":0,"quadreKills":0,"pentaKills":0,"goldEarned":13159,"individualPosition":"JUNGLE","item0":6632,"item1":3071,"item2":3123,"item3":3156,"item4":3047,"item5":3133,"item6":3364,"totalDamageDealt":143338,"summoner1Id":11,"summoner2Id":4,"perks":{"statPerks":{"defense":5002,"flex":5008,"offense":5005},"styles":[{"description":"primaryStyle","selections":[{"perk":8010,"var1":791,"var2":0,"var3":0},{"perk":9111,"var1":742,"var2":280,"var3":0},{"perk":9104,"var1":12,"var2":20,"var3":0},{"perk":8299,"var1":508,"var2":0,"var3":0}],"style":8000},{"description":"subStyle","selections":[{"perk":8347,"var1":0,"var2":0,"var3":0},{"perk":8304,"var1":9,"var2":4,"var3":5}],"style":8300}]},"totalMinionsKilled":20,"win":false},{"summonerName":"해가지면달이핀다","kills":4,"assists":7,"deaths":6,"champLevel":15,"championName":"Vex","detectorWardsPlaced":3,"wardsPlaced":7,"wardsKilled":5,"doubleKills":0,"tripleKills":0,"quadreKills":0,"pentaKills":0,"goldEarned":11076,"individualPosition":"MIDDLE","item0":6653,"item1":3157,"item2":3145,"item3":1082,"item4":1058,"item5":3020,"item6":3364,"totalDamageDealt":129927,"summoner1Id":14,"summoner2Id":4,"perks":{"statPerks":{"defense":5003,"flex":5008,"offense":5005},"styles":[{"description":"primaryStyle","selections":[{"perk":8369,"var1":1155,"var2":849,"var3":0},{"perk":8304,"var1":9,"var2":4,"var3":5},{"perk":8316,"var1":4916,"var2":0,"var3":0},{"perk":8347,"var1":0,"var2":0,"var3":0}],"style":8300},{"description":"subStyle","selections":[{"perk":8139,"var1":732,"var2":0,"var3":0},{"perk":8106,"var1":5,"var2":0,"var3":0}],"style":8100}]},"totalMinionsKilled":199,"win":false},{"summonerName":"dia hermoso","kills":2,"assists":5,"deaths":7,"champLevel":12,"championName":"Lucian","detectorWardsPlaced":4,"wardsPlaced":10,"wardsKilled":6,"doubleKills":0,"tripleKills":0,"quadreKills":0,"pentaKills":0,"goldEarned":9261,"individualPosition":"BOTTOM","item0":6671,"item1":3094,"item2":1018,"item3":1038,"item4":0,"item5":2422,"item6":3363,"totalDamageDealt":94079,"summoner1Id":1,"summoner2Id":4,"perks":{"statPerks":{"defense":5002,"flex":5008,"offense":5005},"styles":[{"description":"primaryStyle","selections":[{"perk":8369,"var1":659,"var2":528,"var3":0},{"perk":8304,"var1":10,"var2":3,"var3":0},{"perk":8345,"var1":3,"var2":0,"var3":0},{"perk":8347,"var1":0,"var2":0,"var3":0}],"style":8300},{"description":"subStyle","selections":[{"perk":8009,"var1":1052,"var2":0,"var3":0},{"perk":9103,"var1":0,"var2":0,"var3":0}],"style":8000}]},"totalMinionsKilled":166,"win":false},{"summonerName":"Gen G Akia","kills":1,"assists":8,"deaths":6,"champLevel":11,"championName":"Nami","detectorWardsPlaced":6,"wardsPlaced":41,"wardsKilled":5,"doubleKills":0,"tripleKills":0,"quadreKills":0,"pentaKills":0,"goldEarned":6252,"individualPosition":"UTILITY","item0":3158,"item1":0,"item2":3853,"item3":3916,"item4":4005,"item5":4642,"item6":3364,"totalDamageDealt":11201,"summoner1Id":7,"summoner2Id":4,"perks":{"statPerks":{"defense":5002,"flex":5008,"offense":5008},"styles":[{"description":"primaryStyle","selections":[{"perk":8112,"var1":648,"var2":0,"var3":0},{"perk":8126,"var1":288,"var2":0,"var3":0},{"perk":8136,"var1":9,"var2":18,"var3":0},{"perk":8135,"var1":400,"var2":4,"var3":0}],"style":8100},{"description":"subStyle","selections":[{"perk":8304,"var1":10,"var2":3,"var3":0},{"perk":8345,"var1":3,"var2":0,"var3":0}],"style":8300}]},"totalMinionsKilled":9,"win":false},{"summonerName":"FIORAKlNG","kills":7,"assists":1,"deaths":3,"champLevel":15,"championName":"Gwen","detectorWardsPlaced":2,"wardsPlaced":6,"wardsKilled":6,"doubleKills":1,"tripleKills":0,"quadreKills":0,"pentaKills":0,"goldEarned":11092,"individualPosition":"TOP","item0":1056,"item1":4633,"item2":4645,"item3":1058,"item4":1058,"item5":3158,"item6":3364,"totalDamageDealt":168939,"summoner1Id":14,"summoner2Id":12,"perks":{"statPerks":{"defense":5002,"flex":5008,"offense":5005},"styles":[{"description":"primaryStyle","selections":[{"perk":8010,"var1":662,"var2":0,"var3":0},{"perk":8009,"var1":1457,"var2":0,"var3":0},{"perk":9104,"var1":16,"var2":30,"var3":0},{"perk":8299,"var1":733,"var2":0,"var3":0}],"style":8000},{"description":"subStyle","selections":[{"perk":8473,"var1":760,"var2":0,"var3":0},{"perk":8242,"var1":64,"var2":0,"var3":0}],"style":8400}]},"totalMinionsKilled":169,"win":true},{"summonerName":"JUGKlNG","kills":11,"assists":10,"deaths":3,"champLevel":14,"championName":"Pantheon","detectorWardsPlaced":8,"wardsPlaced":10,"wardsKilled":4,"doubleKills":0,"tripleKills":0,"quadreKills":0,"pentaKills":0,"goldEarned":12598,"individualPosition":"JUNGLE","item0":0,"item1":6630,"item2":1038,"item3":3156,"item4":6609,"item5":3047,"item6":3364,"totalDamageDealt":158686,"summoner1Id":11,"summoner2Id":4,"perks":{"statPerks":{"defense":5002,"flex":5008,"offense":5005},"styles":[{"description":"primaryStyle","selections":[{"perk":8010,"var1":437,"var2":0,"var3":0},{"perk":9111,"var1":1560,"var2":420,"var3":0},{"perk":9105,"var1":7,"var2":0,"var3":0},{"perk":8014,"var1":602,"var2":0,"var3":0}],"style":8000},{"description":"subStyle","selections":[{"perk":8347,"var1":0,"var2":0,"var3":0},{"perk":8304,"var1":6,"var2":4,"var3":5}],"style":8300}]},"totalMinionsKilled":29,"win":true},{"summonerName":"과일먹고싶다","kills":1,"assists":3,"deaths":10,"champLevel":13,"championName":"Sylas","detectorWardsPlaced":1,"wardsPlaced":5,"wardsKilled":4,"doubleKills":0,"tripleKills":0,"quadreKills":0,"pentaKills":0,"goldEarned":8273,"individualPosition":"MIDDLE","item0":3157,"item1":4644,"item2":1052,"item3":1056,"item4":3158,"item5":1082,"item6":3364,"totalDamageDealt":90565,"summoner1Id":4,"summoner2Id":12,"perks":{"statPerks":{"defense":5003,"flex":5008,"offense":5008},"styles":[{"description":"primaryStyle","selections":[{"perk":8010,"var1":327,"var2":0,"var3":0},{"perk":8009,"var1":1030,"var2":0,"var3":0},{"perk":9105,"var1":20,"var2":50,"var3":0},{"perk":8299,"var1":440,"var2":0,"var3":0}],"style":8000},{"description":"subStyle","selections":[{"perk":8444,"var1":803,"var2":0,"var3":0},{"perk":8451,"var1":172,"var2":0,"var3":0}],"style":8400}]},"totalMinionsKilled":136,"win":true},{"summonerName":"Happie","kills":10,"assists":9,"deaths":3,"champLevel":13,"championName":"Aphelios","detectorWardsPlaced":3,"wardsPlaced":9,"wardsKilled":10,"doubleKills":4,"tripleKills":0,"quadreKills":0,"pentaKills":0,"goldEarned":13716,"individualPosition":"BOTTOM","item0":2420,"item1":3006,"item2":6671,"item3":3031,"item4":3086,"item5":3072,"item6":3363,"totalDamageDealt":147349,"summoner1Id":4,"summoner2Id":7,"perks":{"statPerks":{"defense":5002,"flex":5008,"offense":5005},"styles":[{"description":"primaryStyle","selections":[{"perk":8021,"var1":3219,"var2":2606,"var3":0},{"perk":8009,"var1":2361,"var2":0,"var3":0},{"perk":9103,"var1":12,"var2":0,"var3":0},{"perk":8014,"var1":625,"var2":0,"var3":0}],"style":8000},{"description":"subStyle","selections":[{"perk":8139,"var1":896,"var2":0,"var3":0},{"perk":8134,"var1":19,"var2":5,"var3":0}],"style":8100}]},"totalMinionsKilled":190,"win":true},{"summonerName":"NS Goliath","kills":2,"assists":12,"deaths":3,"champLevel":13,"championName":"TahmKench","detectorWardsPlaced":10,"wardsPlaced":39,"wardsKilled":6,"doubleKills":0,"tripleKills":0,"quadreKills":0,"pentaKills":0,"goldEarned":7602,"individualPosition":"UTILITY","item0":3190,"item1":3140,"item2":3860,"item3":2055,"item4":3067,"item5":3047,"item6":3364,"totalDamageDealt":29017,"summoner1Id":4,"summoner2Id":3,"perks":{"statPerks":{"defense":5002,"flex":5003,"offense":5005},"styles":[{"description":"primaryStyle","selections":[{"perk":8465,"var1":1158,"var2":0,"var3":0},{"perk":8463,"var1":730,"var2":0,"var3":0},{"perk":8473,"var1":498,"var2":0,"var3":0},{"perk":8242,"var1":79,"var2":0,"var3":0}],"style":8400},{"description":"subStyle","selections":[{"perk":8410,"var1":51,"var2":0,"var3":0},{"perk":8316,"var1":571,"var2":0,"var3":0}],"style":8300}]},"totalMinionsKilled":41,"win":true}]},{"summonerName":"JUGKlNG","gameStartTimestamp":1659789584770,"gameEndTimestamp":1659790541802,"gameId":6060451008,"gameDuration":957,"gameMode":"CLASSIC","totalKills":7,"participants":[{"summonerName":"하건둘리","kills":2,"assists":1,"deaths":3,"champLevel":10,"championName":"Renekton","detectorWardsPlaced":2,"wardsPlaced":6,"wardsKilled":0,"doubleKills":0,"tripleKills":0,"quadreKills":0,"pentaKills":0,"goldEarned":6827,"individualPosition":"TOP","item0":2055,"item1":1055,"item2":3133,"item3":3134,"item4":3153,"item5":2422,"item6":3364,"totalDamageDealt":65617,"summoner1Id":4,"summoner2Id":12,"perks":{"statPerks":{"defense":5003,"flex":5008,"offense":5008},"styles":[{"description":"primaryStyle","selections":[{"perk":8005,"var1":817,"var2":442,"var3":374},{"perk":9111,"var1":222,"var2":60,"var3":0},{"perk":9104,"var1":0,"var2":0,"var3":0},{"perk":8299,"var1":456,"var2":0,"var3":0}],"style":8000},{"description":"subStyle","selections":[{"perk":8304,"var1":11,"var2":1,"var3":5},{"perk":8347,"var1":0,"var2":0,"var3":0}],"style":8300}]},"totalMinionsKilled":120,"win":false},{"summonerName":"Dan Xiao Gu","kills":1,"assists":2,"deaths":3,"champLevel":9,"championName":"JarvanIV","detectorWardsPlaced":2,"wardsPlaced":3,"wardsKilled":2,"doubleKills":0,"tripleKills":0,"quadreKills":0,"pentaKills":0,"goldEarned":5629,"individualPosition":"JUNGLE","item0":6630,"item1":2055,"item2":1036,"item3":3123,"item4":2422,"item5":1036,"item6":3364,"totalDamageDealt":73798,"summoner1Id":11,"summoner2Id":4,"perks":{"statPerks":{"defense":5002,"flex":5008,"offense":5005},"styles":[{"description":"primaryStyle","selections":[{"perk":8010,"var1":18,"var2":0,"var3":0},{"perk":9111,"var1":82,"var2":60,"var3":0},{"perk":9105,"var1":0,"var2":0,"var3":0},{"perk":8014,"var1":98,"var2":0,"var3":0}],"style":8000},{"description":"subStyle","selections":[{"perk":8304,"var1":10,"var2":3,"var3":0},{"perk":8347,"var1":0,"var2":0,"var3":0}],"style":8300}]},"totalMinionsKilled":12,"win":false},{"summonerName":"또 한 방울","kills":2,"assists":1,"deaths":3,"champLevel":10,"championName":"Akali","detectorWardsPlaced":0,"wardsPlaced":2,"wardsKilled":3,"doubleKills":0,"tripleKills":0,"quadreKills":0,"pentaKills":0,"goldEarned":5860,"individualPosition":"MIDDLE","item0":1054,"item1":3020,"item2":3152,"item3":1082,"item4":0,"item5":0,"item6":3364,"totalDamageDealt":48751,"summoner1Id":12,"summoner2Id":4,"perks":{"statPerks":{"defense":5003,"flex":5008,"offense":5008},"styles":[{"description":"primaryStyle","selections":[{"perk":8010,"var1":266,"var2":0,"var3":0},{"perk":8009,"var1":249,"var2":0,"var3":0},{"perk":9105,"var1":0,"var2":0,"var3":0},{"perk":8299,"var1":166,"var2":0,"var3":0}],"style":8000},{"description":"subStyle","selections":[{"perk":8444,"var1":442,"var2":0,"var3":0},{"perk":8242,"var1":28,"var2":0,"var3":0}],"style":8400}]},"totalMinionsKilled":117,"win":false},{"summonerName":"귀염둥이현택잉","kills":2,"assists":0,"deaths":8,"champLevel":8,"championName":"Aphelios","detectorWardsPlaced":3,"wardsPlaced":7,"wardsKilled":3,"doubleKills":0,"tripleKills":0,"quadreKills":0,"pentaKills":0,"goldEarned":5240,"individualPosition":"BOTTOM","item0":1053,"item1":2031,"item2":1037,"item3":1043,"item4":1036,"item5":3006,"item6":3340,"totalDamageDealt":47282,"summoner1Id":6,"summoner2Id":4,"perks":{"statPerks":{"defense":5002,"flex":5008,"offense":5005},"styles":[{"description":"primaryStyle","selections":[{"perk":8008,"var1":24,"var2":2,"var3":0},{"perk":8009,"var1":375,"var2":0,"var3":0},{"perk":9104,"var1":0,"var2":0,"var3":0},{"perk":8017,"var1":520,"var2":0,"var3":0}],"style":8000},{"description":"subStyle","selections":[{"perk":8275,"var1":7,"var2":0,"var3":0},{"perk":8236,"var1":4,"var2":0,"var3":0}],"style":8200}]},"totalMinionsKilled":106,"win":false},{"summonerName":"wodewenti","kills":0,"assists":5,"deaths":5,"champLevel":8,"championName":"Blitzcrank","detectorWardsPlaced":6,"wardsPlaced":13,"wardsKilled":5,"doubleKills":0,"tripleKills":0,"quadreKills":0,"pentaKills":0,"goldEarned":4086,"individualPosition":"UTILITY","item0":3855,"item1":4642,"item2":3067,"item3":2055,"item4":0,"item5":3009,"item6":3364,"totalDamageDealt":12786,"summoner1Id":4,"summoner2Id":14,"perks":{"statPerks":{"defense":5003,"flex":5002,"offense":5007},"styles":[{"description":"primaryStyle","selections":[{"perk":8351,"var1":38,"var2":784,"var3":0},{"perk":8306,"var1":2,"var2":0,"var3":0},{"perk":8345,"var1":3,"var2":0,"var3":0},{"perk":8347,"var1":0,"var2":0,"var3":0}],"style":8300},{"description":"subStyle","selections":[{"perk":8242,"var1":37,"var2":0,"var3":0},{"perk":8444,"var1":519,"var2":0,"var3":0}],"style":8400}]},"totalMinionsKilled":27,"win":false},{"summonerName":"JUGKlNG","kills":4,"assists":4,"deaths":2,"champLevel":11,"championName":"Sylas","detectorWardsPlaced":2,"wardsPlaced":3,"wardsKilled":3,"doubleKills":0,"tripleKills":0,"quadreKills":0,"pentaKills":0,"goldEarned":6111,"individualPosition":"TOP","item0":6656,"item1":2031,"item2":0,"item3":1029,"item4":1054,"item5":3158,"item6":3363,"totalDamageDealt":56087,"summoner1Id":12,"summoner2Id":4,"perks":{"statPerks":{"defense":5002,"flex":5008,"offense":5008},"styles":[{"description":"primaryStyle","selections":[{"perk":8010,"var1":260,"var2":0,"var3":0},{"perk":8009,"var1":1703,"var2":0,"var3":0},{"perk":9105,"var1":15,"var2":30,"var3":0},{"perk":8299,"var1":619,"var2":0,"var3":0}],"style":8000},{"description":"subStyle","selections":[{"perk":8444,"var1":696,"var2":0,"var3":0},{"perk":8242,"var1":39,"var2":0,"var3":0}],"style":8400}]},"totalMinionsKilled":110,"win":true},{"summonerName":"과일먹고싶다","kills":7,"assists":9,"deaths":0,"champLevel":10,"championName":"LeeSin","detectorWardsPlaced":5,"wardsPlaced":10,"wardsKilled":2,"doubleKills":0,"tripleKills":0,"quadreKills":0,"pentaKills":0,"goldEarned":7113,"individualPosition":"JUNGLE","item0":6630,"item1":0,"item2":2031,"item3":3133,"item4":3158,"item5":0,"item6":3340,"totalDamageDealt":78469,"summoner1Id":4,"summoner2Id":11,"perks":{"statPerks":{"defense":5002,"flex":5008,"offense":5005},"styles":[{"description":"primaryStyle","selections":[{"perk":8010,"var1":131,"var2":0,"var3":0},{"perk":9111,"var1":697,"var2":320,"var3":0},{"perk":9104,"var1":9,"var2":20,"var3":0},{"perk":8014,"var1":324,"var2":0,"var3":0}],"style":8000},{"description":"subStyle","selections":[{"perk":8304,"var1":8,"var2":1,"var3":5},{"perk":8347,"var1":0,"var2":0,"var3":0}],"style":8300}]},"totalMinionsKilled":9,"win":true},{"summonerName":"HLE Karis1","kills":2,"assists":4,"deaths":0,"champLevel":11,"championName":"Ryze","detectorWardsPlaced":3,"wardsPlaced":5,"wardsKilled":2,"doubleKills":0,"tripleKills":0,"quadreKills":0,"pentaKills":0,"goldEarned":6425,"individualPosition":"MIDDLE","item0":4644,"item1":2423,"item2":3070,"item3":3158,"item4":3067,"item5":2055,"item6":3364,"totalDamageDealt":73471,"summoner1Id":4,"summoner2Id":12,"perks":{"statPerks":{"defense":5001,"flex":5008,"offense":5005},"styles":[{"description":"primaryStyle","selections":[{"perk":8360,"var1":6,"var2":0,"var3":0},{"perk":8313,"var1":0,"var2":0,"var3":0},{"perk":8345,"var1":3,"var2":0,"var3":0},{"perk":8352,"var1":30,"var2":96,"var3":27}],"style":8300},{"description":"subStyle","selections":[{"perk":8232,"var1":1,"var2":40,"var3":0},{"perk":8226,"var1":250,"var2":760,"var3":0}],"style":8200}]},"totalMinionsKilled":143,"win":true},{"summonerName":"Chancedong","kills":6,"assists":6,"deaths":4,"champLevel":10,"championName":"Sivir","detectorWardsPlaced":1,"wardsPlaced":6,"wardsKilled":1,"doubleKills":0,"tripleKills":0,"quadreKills":0,"pentaKills":0,"goldEarned":7425,"individualPosition":"BOTTOM","item0":2055,"item1":3086,"item2":1036,"item3":6672,"item4":3006,"item5":1055,"item6":3363,"totalDamageDealt":70773,"summoner1Id":6,"summoner2Id":4,"perks":{"statPerks":{"defense":5002,"flex":5008,"offense":5005},"styles":[{"description":"primaryStyle","selections":[{"perk":8008,"var1":41,"var2":10,"var3":0},{"perk":8009,"var1":1239,"var2":0,"var3":0},{"perk":9103,"var1":14,"var2":30,"var3":0},{"perk":8017,"var1":206,"var2":0,"var3":0}],"style":8000},{"description":"subStyle","selections":[{"perk":8236,"var1":4,"var2":0,"var3":0},{"perk":8233,"var1":9,"var2":0,"var3":0}],"style":8200}]},"totalMinionsKilled":116,"win":true},{"summonerName":"NS 피터","kills":3,"assists":14,"deaths":1,"champLevel":9,"championName":"Yuumi","detectorWardsPlaced":3,"wardsPlaced":13,"wardsKilled":2,"doubleKills":0,"tripleKills":0,"quadreKills":0,"pentaKills":0,"goldEarned":6021,"individualPosition":"UTILITY","item0":3853,"item1":2065,"item2":3011,"item3":0,"item4":0,"item5":0,"item6":3364,"totalDamageDealt":8143,"summoner1Id":3,"summoner2Id":14,"perks":{"statPerks":{"defense":5002,"flex":5008,"offense":5008},"styles":[{"description":"primaryStyle","selections":[{"perk":8465,"var1":521,"var2":0,"var3":0},{"perk":8401,"var1":317,"var2":0,"var3":0},{"perk":8473,"var1":204,"var2":0,"var3":0},{"perk":8453,"var1":570,"var2":475,"var3":0}],"style":8400},{"description":"subStyle","selections":[{"perk":8009,"var1":1835,"var2":0,"var3":0},{"perk":8017,"var1":228,"var2":0,"var3":0}],"style":8000}]},"totalMinionsKilled":9,"win":true}]},{"summonerName":"JUGKlNG","gameStartTimestamp":1659787290173,"gameEndTimestamp":1659789163121,"gameId":6060403143,"gameDuration":1872,"gameMode":"CLASSIC","totalKills":36,"participants":[{"summonerName":"Iris to you","kills":4,"assists":12,"deaths":7,"champLevel":16,"championName":"Gwen","detectorWardsPlaced":4,"wardsPlaced":9,"wardsKilled":4,"doubleKills":0,"tripleKills":0,"quadreKills":0,"pentaKills":0,"goldEarned":11723,"individualPosition":"TOP","item0":6656,"item1":4645,"item2":0,"item3":3089,"item4":0,"item5":3111,"item6":3364,"totalDamageDealt":180637,"summoner1Id":3,"summoner2Id":12,"perks":{"statPerks":{"defense":5003,"flex":5008,"offense":5005},"styles":[{"description":"primaryStyle","selections":[{"perk":8010,"var1":910,"var2":0,"var3":0},{"perk":8009,"var1":2247,"var2":0,"var3":0},{"perk":9104,"var1":18,"var2":40,"var3":0},{"perk":8299,"var1":865,"var2":0,"var3":0}],"style":8000},{"description":"subStyle","selections":[{"perk":8444,"var1":1073,"var2":0,"var3":0},{"perk":8242,"var1":74,"var2":0,"var3":0}],"style":8400}]},"totalMinionsKilled":198,"win":false},{"summonerName":"NS Sylvie","kills":15,"assists":11,"deaths":5,"champLevel":16,"championName":"Pantheon","detectorWardsPlaced":6,"wardsPlaced":8,"wardsKilled":11,"doubleKills":3,"tripleKills":0,"quadreKills":0,"pentaKills":0,"goldEarned":15292,"individualPosition":"JUNGLE","item0":3111,"item1":6630,"item2":2421,"item3":3071,"item4":6609,"item5":3156,"item6":3364,"totalDamageDealt":194006,"summoner1Id":11,"summoner2Id":4,"perks":{"statPerks":{"defense":5002,"flex":5008,"offense":5005},"styles":[{"description":"primaryStyle","selections":[{"perk":8010,"var1":1072,"var2":0,"var3":0},{"perk":9111,"var1":3152,"var2":520,"var3":0},{"perk":9104,"var1":11,"var2":0,"var3":0},{"perk":8299,"var1":1480,"var2":0,"var3":0}],"style":8000},{"description":"subStyle","selections":[{"perk":8304,"var1":8,"var2":1,"var3":5},{"perk":8347,"var1":0,"var2":0,"var3":0}],"style":8300}]},"totalMinionsKilled":36,"win":false},{"summonerName":"도리도리 잼젬","kills":5,"assists":16,"deaths":9,"champLevel":16,"championName":"Sylas","detectorWardsPlaced":2,"wardsPlaced":5,"wardsKilled":10,"doubleKills":2,"tripleKills":0,"quadreKills":0,"pentaKills":0,"goldEarned":12991,"individualPosition":"MIDDLE","item0":3157,"item1":4645,"item2":6656,"item3":3020,"item4":0,"item5":3102,"item6":3364,"totalDamageDealt":148558,"summoner1Id":4,"summoner2Id":12,"perks":{"statPerks":{"defense":5003,"flex":5008,"offense":5008},"styles":[{"description":"primaryStyle","selections":[{"perk":8369,"var1":249,"var2":264,"var3":0},{"perk":8304,"var1":9,"var2":0,"var3":0},{"perk":8345,"var1":3,"var2":0,"var3":0},{"perk":8347,"var1":0,"var2":0,"var3":0}],"style":8300},{"description":"subStyle","selections":[{"perk":8444,"var1":1074,"var2":0,"var3":0},{"perk":8242,"var1":63,"var2":0,"var3":0}],"style":8400}]},"totalMinionsKilled":220,"win":false},{"summonerName":"Dan Xiao Gu","kills":10,"assists":13,"deaths":8,"champLevel":15,"championName":"Samira","detectorWardsPlaced":2,"wardsPlaced":10,"wardsKilled":7,"doubleKills":3,"tripleKills":2,"quadreKills":0,"pentaKills":0,"goldEarned":15713,"individualPosition":"BOTTOM","item0":2420,"item1":6676,"item2":3036,"item3":6673,"item4":3031,"item5":3047,"item6":3363,"totalDamageDealt":159697,"summoner1Id":1,"summoner2Id":4,"perks":{"statPerks":{"defense":5002,"flex":5008,"offense":5005},"styles":[{"description":"primaryStyle","selections":[{"perk":8010,"var1":271,"var2":0,"var3":0},{"perk":8009,"var1":1685,"var2":0,"var3":0},{"perk":9103,"var1":18,"var2":30,"var3":0},{"perk":8014,"var1":496,"var2":0,"var3":0}],"style":8000},{"description":"subStyle","selections":[{"perk":8139,"var1":814,"var2":0,"var3":0},{"perk":8135,"var1":550,"var2":5,"var3":0}],"style":8100}]},"totalMinionsKilled":227,"win":false},{"summonerName":"xxxxxxm","kills":2,"assists":21,"deaths":7,"champLevel":13,"championName":"Rell","detectorWardsPlaced":14,"wardsPlaced":48,"wardsKilled":10,"doubleKills":0,"tripleKills":0,"quadreKills":0,"pentaKills":0,"goldEarned":8342,"individualPosition":"UTILITY","item0":3860,"item1":2055,"item2":4401,"item3":3158,"item4":3001,"item5":0,"item6":3364,"totalDamageDealt":23709,"summoner1Id":14,"summoner2Id":4,"perks":{"statPerks":{"defense":5003,"flex":5002,"offense":5008},"styles":[{"description":"primaryStyle","selections":[{"perk":8351,"var1":51,"var2":957,"var3":0},{"perk":8306,"var1":8,"var2":0,"var3":0},{"perk":8316,"var1":649,"var2":0,"var3":0},{"perk":8347,"var1":0,"var2":0,"var3":0}],"style":8300},{"description":"subStyle","selections":[{"perk":8473,"var1":512,"var2":0,"var3":0},{"perk":8242,"var1":132,"var2":0,"var3":0}],"style":8400}]},"totalMinionsKilled":39,"win":false},{"summonerName":"TwitchTV Migung","kills":1,"assists":13,"deaths":8,"champLevel":16,"championName":"Kennen","detectorWardsPlaced":0,"wardsPlaced":11,"wardsKilled":0,"doubleKills":0,"tripleKills":0,"quadreKills":0,"pentaKills":0,"goldEarned":11640,"individualPosition":"TOP","item0":4645,"item1":2424,"item2":3135,"item3":3020,"item4":4633,"item5":0,"item6":3363,"totalDamageDealt":108360,"summoner1Id":12,"summoner2Id":4,"perks":{"statPerks":{"defense":5003,"flex":5008,"offense":5005},"styles":[{"description":"primaryStyle","selections":[{"perk":8369,"var1":667,"var2":533,"var3":0},{"perk":8313,"var1":0,"var2":0,"var3":0},{"perk":8321,"var1":5,"var2":0,"var3":0},{"perk":8347,"var1":0,"var2":0,"var3":0}],"style":8300},{"description":"subStyle","selections":[{"perk":8275,"var1":9,"var2":0,"var3":0},{"perk":8237,"var1":455,"var2":0,"var3":0}],"style":8200}]},"totalMinionsKilled":159,"win":true},{"summonerName":"JUGKlNG","kills":5,"assists":20,"deaths":11,"champLevel":15,"championName":"XinZhao","detectorWardsPlaced":9,"wardsPlaced":12,"wardsKilled":5,"doubleKills":0,"tripleKills":0,"quadreKills":0,"pentaKills":0,"goldEarned":10942,"individualPosition":"JUNGLE","item0":0,"item1":6630,"item2":0,"item3":3155,"item4":6609,"item5":3047,"item6":3364,"totalDamageDealt":105178,"summoner1Id":11,"summoner2Id":4,"perks":{"statPerks":{"defense":5002,"flex":5008,"offense":5005},"styles":[{"description":"primaryStyle","selections":[{"perk":8010,"var1":563,"var2":0,"var3":0},{"perk":9111,"var1":1617,"var2":500,"var3":0},{"perk":9105,"var1":14,"var2":50,"var3":0},{"perk":8014,"var1":583,"var2":0,"var3":0}],"style":8000},{"description":"subStyle","selections":[{"perk":8304,"var1":9,"var2":4,"var3":5},{"perk":8347,"var1":0,"var2":0,"var3":0}],"style":8300}]},"totalMinionsKilled":15,"win":true},{"summonerName":"HLE Karis1","kills":20,"assists":8,"deaths":6,"champLevel":18,"championName":"Azir","detectorWardsPlaced":4,"wardsPlaced":6,"wardsKilled":11,"doubleKills":3,"tripleKills":0,"quadreKills":0,"pentaKills":0,"goldEarned":20234,"individualPosition":"MIDDLE","item0":4644,"item1":3157,"item2":3135,"item3":3020,"item4":3089,"item5":3115,"item6":3364,"totalDamageDealt":267139,"summoner1Id":4,"summoner2Id":12,"perks":{"statPerks":{"defense":5003,"flex":5008,"offense":5005},"styles":[{"description":"primaryStyle","selections":[{"perk":8010,"var1":723,"var2":0,"var3":0},{"perk":8009,"var1":5067,"var2":0,"var3":0},{"perk":9104,"var1":13,"var2":30,"var3":0},{"perk":8014,"var1":1337,"var2":0,"var3":0}],"style":8000},{"description":"subStyle","selections":[{"perk":8226,"var1":250,"var2":676,"var3":0},{"perk":8210,"var1":33,"var2":0,"var3":0}],"style":8200}]},"totalMinionsKilled":276,"win":true},{"summonerName":"kaixinwan","kills":7,"assists":18,"deaths":6,"champLevel":16,"championName":"Ezreal","detectorWardsPlaced":3,"wardsPlaced":13,"wardsKilled":4,"doubleKills":1,"tripleKills":0,"quadreKills":0,"pentaKills":0,"goldEarned":15571,"individualPosition":"BOTTOM","item0":3026,"item1":3042,"item2":3158,"item3":6694,"item4":2055,"item5":3078,"item6":3363,"totalDamageDealt":201264,"summoner1Id":4,"summoner2Id":1,"perks":{"statPerks":{"defense":5002,"flex":5008,"offense":5005},"styles":[{"description":"primaryStyle","selections":[{"perk":8369,"var1":1506,"var2":1073,"var3":0},{"perk":8304,"var1":11,"var2":1,"var3":5},{"perk":8345,"var1":3,"var2":0,"var3":0},{"perk":8347,"var1":0,"var2":0,"var3":0}],"style":8300},{"description":"subStyle","selections":[{"perk":8009,"var1":7690,"var2":0,"var3":0},{"perk":9103,"var1":21,"var2":10,"var3":0}],"style":8000}]},"totalMinionsKilled":220,"win":true},{"summonerName":"호잇이","kills":3,"assists":26,"deaths":5,"champLevel":15,"championName":"Yuumi","detectorWardsPlaced":8,"wardsPlaced":41,"wardsKilled":12,"doubleKills":1,"tripleKills":0,"quadreKills":0,"pentaKills":0,"goldEarned":9510,"individualPosition":"UTILITY","item0":3504,"item1":2055,"item2":1004,"item3":3011,"item4":6617,"item5":3853,"item6":3364,"totalDamageDealt":12858,"summoner1Id":3,"summoner2Id":14,"perks":{"statPerks":{"defense":5002,"flex":5008,"offense":5008},"styles":[{"description":"primaryStyle","selections":[{"perk":8465,"var1":2875,"var2":0,"var3":0},{"perk":8401,"var1":610,"var2":0,"var3":0},{"perk":8473,"var1":515,"var2":0,"var3":0},{"perk":8453,"var1":1703,"var2":822,"var3":0}],"style":8400},{"description":"subStyle","selections":[{"perk":8009,"var1":3465,"var2":0,"var3":0},{"perk":8017,"var1":575,"var2":0,"var3":0}],"style":8000}]},"totalMinionsKilled":19,"win":true}]},{"summonerName":"JUGKlNG","gameStartTimestamp":1659780737119,"gameEndTimestamp":1659782695088,"gameId":6060025907,"gameDuration":1957,"gameMode":"CLASSIC","totalKills":22,"participants":[{"summonerName":"하건펭수","kills":3,"assists":6,"deaths":8,"champLevel":17,"championName":"Gwen","detectorWardsPlaced":3,"wardsPlaced":6,"wardsKilled":13,"doubleKills":0,"tripleKills":0,"quadreKills":0,"pentaKills":0,"goldEarned":13623,"individualPosition":"TOP","item0":1029,"item1":3108,"item2":3089,"item3":4645,"item4":4633,"item5":3020,"item6":3364,"totalDamageDealt":238505,"summoner1Id":12,"summoner2Id":14,"perks":{"statPerks":{"defense":5003,"flex":5008,"offense":5005},"styles":[{"description":"primaryStyle","selections":[{"perk":8010,"var1":270,"var2":0,"var3":0},{"perk":8009,"var1":1748,"var2":0,"var3":0},{"perk":9105,"var1":18,"var2":40,"var3":0},{"perk":8299,"var1":606,"var2":0,"var3":0}],"style":8000},{"description":"subStyle","selections":[{"perk":8446,"var1":1490,"var2":0,"var3":0},{"perk":8444,"var1":841,"var2":0,"var3":0}],"style":8400}]},"totalMinionsKilled":244,"win":false},{"summonerName":"몽키데이 ","kills":4,"assists":9,"deaths":6,"champLevel":14,"championName":"RekSai","detectorWardsPlaced":7,"wardsPlaced":8,"wardsKilled":5,"doubleKills":0,"tripleKills":0,"quadreKills":0,"pentaKills":0,"goldEarned":11580,"individualPosition":"JUNGLE","item0":3814,"item1":3156,"item2":6693,"item3":0,"item4":3158,"item5":2421,"item6":3364,"totalDamageDealt":131058,"summoner1Id":4,"summoner2Id":11,"perks":{"statPerks":{"defense":5002,"flex":5008,"offense":5005},"styles":[{"description":"primaryStyle","selections":[{"perk":8010,"var1":281,"var2":0,"var3":0},{"perk":9111,"var1":931,"var2":260,"var3":0},{"perk":9104,"var1":14,"var2":10,"var3":0},{"perk":8014,"var1":313,"var2":0,"var3":0}],"style":8000},{"description":"subStyle","selections":[{"perk":8304,"var1":10,"var2":3,"var3":0},{"perk":8347,"var1":0,"var2":0,"var3":0}],"style":8300}]},"totalMinionsKilled":14,"win":false},{"summonerName":"cikcik","kills":4,"assists":9,"deaths":6,"champLevel":17,"championName":"Azir","detectorWardsPlaced":6,"wardsPlaced":14,"wardsKilled":11,"doubleKills":1,"tripleKills":0,"quadreKills":0,"pentaKills":0,"goldEarned":13971,"individualPosition":"MIDDLE","item0":3115,"item1":3102,"item2":2420,"item3":4644,"item4":3020,"item5":3135,"item6":3363,"totalDamageDealt":202490,"summoner1Id":12,"summoner2Id":4,"perks":{"statPerks":{"defense":5003,"flex":5008,"offense":5005},"styles":[{"description":"primaryStyle","selections":[{"perk":8010,"var1":354,"var2":0,"var3":0},{"perk":8009,"var1":3459,"var2":0,"var3":0},{"perk":9104,"var1":18,"var2":10,"var3":0},{"perk":8014,"var1":369,"var2":0,"var3":0}],"style":8000},{"description":"subStyle","selections":[{"perk":8226,"var1":250,"var2":541,"var3":0},{"perk":8237,"var1":667,"var2":0,"var3":0}],"style":8200}]},"totalMinionsKilled":271,"win":false},{"summonerName":"귀염둥이현택잉","kills":7,"assists":5,"deaths":10,"champLevel":15,"championName":"Kalista","detectorWardsPlaced":6,"wardsPlaced":15,"wardsKilled":11,"doubleKills":1,"tripleKills":0,"quadreKills":0,"pentaKills":0,"goldEarned":14153,"individualPosition":"BOTTOM","item0":3124,"item1":3143,"item2":6673,"item3":3091,"item4":0,"item5":3006,"item6":3363,"totalDamageDealt":166903,"summoner1Id":1,"summoner2Id":4,"perks":{"statPerks":{"defense":5002,"flex":5008,"offense":5005},"styles":[{"description":"primaryStyle","selections":[{"perk":8008,"var1":72,"var2":12,"var3":0},{"perk":9111,"var1":825,"var2":240,"var3":0},{"perk":9104,"var1":16,"var2":20,"var3":0},{"perk":8299,"var1":1335,"var2":0,"var3":0}],"style":8000},{"description":"subStyle","selections":[{"perk":8139,"var1":577,"var2":0,"var3":0},{"perk":8135,"var1":400,"var2":4,"var3":0}],"style":8100}]},"totalMinionsKilled":225,"win":false},{"summonerName":"NS Goliath","kills":4,"assists":10,"deaths":10,"champLevel":13,"championName":"Renata","detectorWardsPlaced":16,"wardsPlaced":79,"wardsKilled":20,"doubleKills":0,"tripleKills":0,"quadreKills":0,"pentaKills":0,"goldEarned":10448,"individualPosition":"UTILITY","item0":2065,"item1":3853,"item2":0,"item3":3011,"item4":8001,"item5":3158,"item6":3364,"totalDamageDealt":24845,"summoner1Id":4,"summoner2Id":14,"perks":{"statPerks":{"defense":5002,"flex":5003,"offense":5005},"styles":[{"description":"primaryStyle","selections":[{"perk":8465,"var1":2461,"var2":0,"var3":0},{"perk":8401,"var1":290,"var2":0,"var3":0},{"perk":8473,"var1":949,"var2":0,"var3":0},{"perk":8242,"var1":92,"var2":0,"var3":0}],"style":8400},{"description":"subStyle","selections":[{"perk":8136,"var1":30,"var2":30,"var3":0},{"perk":8105,"var1":13,"var2":5,"var3":0}],"style":8100}]},"totalMinionsKilled":29,"win":false},{"summonerName":"신을저주해","kills":7,"assists":9,"deaths":4,"champLevel":18,"championName":"Vladimir","detectorWardsPlaced":5,"wardsPlaced":9,"wardsKilled":4,"doubleKills":0,"tripleKills":0,"quadreKills":0,"pentaKills":0,"goldEarned":14472,"individualPosition":"TOP","item0":4636,"item1":3157,"item2":4629,"item3":1082,"item4":3135,"item5":3158,"item6":3364,"totalDamageDealt":222827,"summoner1Id":14,"summoner2Id":6,"perks":{"statPerks":{"defense":5003,"flex":5008,"offense":5008},"styles":[{"description":"primaryStyle","selections":[{"perk":8214,"var1":1781,"var2":0,"var3":0},{"perk":8275,"var1":13,"var2":0,"var3":0},{"perk":8234,"var1":15537,"var2":0,"var3":0},{"perk":8237,"var1":626,"var2":0,"var3":0}],"style":8200},{"description":"subStyle","selections":[{"perk":9105,"var1":17,"var2":20,"var3":0},{"perk":8299,"var1":1627,"var2":0,"var3":0}],"style":8000}]},"totalMinionsKilled":253,"win":true},{"summonerName":"JUGKlNG","kills":10,"assists":15,"deaths":6,"champLevel":17,"championName":"Viego","detectorWardsPlaced":9,"wardsPlaced":11,"wardsKilled":14,"doubleKills":0,"tripleKills":0,"quadreKills":0,"pentaKills":0,"goldEarned":13682,"individualPosition":"JUNGLE","item0":2055,"item1":3026,"item2":3051,"item3":6609,"item4":6632,"item5":3047,"item6":3364,"totalDamageDealt":151479,"summoner1Id":11,"summoner2Id":4,"perks":{"statPerks":{"defense":5002,"flex":5008,"offense":5005},"styles":[{"description":"primaryStyle","selections":[{"perk":8010,"var1":559,"var2":0,"var3":0},{"perk":9111,"var1":1919,"var2":500,"var3":0},{"perk":9104,"var1":13,"var2":0,"var3":0},{"perk":8014,"var1":839,"var2":0,"var3":0}],"style":8000},{"description":"subStyle","selections":[{"perk":8304,"var1":10,"var2":3,"var3":0},{"perk":8347,"var1":0,"var2":0,"var3":0}],"style":8300}]},"totalMinionsKilled":19,"win":true},{"summonerName":"미북이","kills":5,"assists":13,"deaths":5,"champLevel":17,"championName":"Taliyah","detectorWardsPlaced":5,"wardsPlaced":15,"wardsKilled":10,"doubleKills":0,"tripleKills":0,"quadreKills":0,"pentaKills":0,"goldEarned":13830,"individualPosition":"MIDDLE","item0":3040,"item1":6655,"item2":3102,"item3":0,"item4":3135,"item5":3158,"item6":3363,"totalDamageDealt":210559,"summoner1Id":12,"summoner2Id":4,"perks":{"statPerks":{"defense":5003,"flex":5008,"offense":5005},"styles":[{"description":"primaryStyle","selections":[{"perk":8360,"var1":13,"var2":0,"var3":0},{"perk":8313,"var1":0,"var2":0,"var3":0},{"perk":8316,"var1":1962,"var2":0,"var3":0},{"perk":8347,"var1":0,"var2":0,"var3":0}],"style":8300},{"description":"subStyle","selections":[{"perk":8226,"var1":250,"var2":1165,"var3":0},{"perk":8234,"var1":14242,"var2":0,"var3":0}],"style":8200}]},"totalMinionsKilled":208,"win":true},{"summonerName":"호잇이","kills":17,"assists":13,"deaths":3,"champLevel":18,"championName":"Sivir","detectorWardsPlaced":2,"wardsPlaced":13,"wardsKilled":26,"doubleKills":4,"tripleKills":0,"quadreKills":0,"pentaKills":0,"goldEarned":20855,"individualPosition":"BOTTOM","item0":6672,"item1":3031,"item2":3046,"item3":3026,"item4":3156,"item5":3072,"item6":3363,"totalDamageDealt":299670,"summoner1Id":4,"summoner2Id":7,"perks":{"statPerks":{"defense":5002,"flex":5008,"offense":5005},"styles":[{"description":"primaryStyle","selections":[{"perk":8008,"var1":51,"var2":2,"var3":0},{"perk":8009,"var1":4406,"var2":0,"var3":0},{"perk":9103,"var1":13,"var2":50,"var3":0},{"perk":8017,"var1":821,"var2":0,"var3":0}],"style":8000},{"description":"subStyle","selections":[{"perk":8304,"var1":8,"var2":1,"var3":5},{"perk":8345,"var1":3,"var2":0,"var3":0}],"style":8300}]},"totalMinionsKilled":307,"win":true},{"summonerName":"DK Bible","kills":1,"assists":18,"deaths":4,"champLevel":14,"championName":"Leona","detectorWardsPlaced":17,"wardsPlaced":57,"wardsKilled":19,"doubleKills":0,"tripleKills":0,"quadreKills":0,"pentaKills":0,"goldEarned":8720,"individualPosition":"UTILITY","item0":3001,"item1":3067,"item2":1011,"item3":3860,"item4":0,"item5":3111,"item6":3364,"totalDamageDealt":14509,"summoner1Id":14,"summoner2Id":4,"perks":{"statPerks":{"defense":5002,"flex":5002,"offense":5007},"styles":[{"description":"primaryStyle","selections":[{"perk":8351,"var1":55,"var2":559,"var3":0},{"perk":8306,"var1":5,"var2":0,"var3":0},{"perk":8316,"var1":200,"var2":0,"var3":0},{"perk":8347,"var1":0,"var2":0,"var3":0}],"style":8300},{"description":"subStyle","selections":[{"perk":8242,"var1":40,"var2":0,"var3":0},{"perk":8444,"var1":943,"var2":0,"var3":0}],"style":8400}]},"totalMinionsKilled":42,"win":true}]},{"summonerName":"JUGKlNG","gameStartTimestamp":1659547825759,"gameEndTimestamp":1659548992176,"gameId":6055744450,"gameDuration":1166,"gameMode":"CLASSIC","totalKills":38,"participants":[{"summonerName":"갈과 배 음료","kills":6,"assists":2,"deaths":1,"champLevel":13,"championName":"Renekton","detectorWardsPlaced":2,"wardsPlaced":6,"wardsKilled":2,"doubleKills":0,"tripleKills":0,"quadreKills":0,"pentaKills":0,"goldEarned":10052,"individualPosition":"TOP","item0":6693,"item1":1036,"item2":1054,"item3":3153,"item4":3047,"item5":1036,"item6":3364,"totalDamageDealt":111834,"summoner1Id":14,"summoner2Id":4,"perks":{"statPerks":{"defense":5003,"flex":5008,"offense":5008},"styles":[{"description":"primaryStyle","selections":[{"perk":8010,"var1":173,"var2":0,"var3":0},{"perk":9111,"var1":533,"var2":160,"var3":0},{"perk":9105,"var1":14,"var2":30,"var3":0},{"perk":8299,"var1":288,"var2":0,"var3":0}],"style":8000},{"description":"subStyle","selections":[{"perk":8444,"var1":855,"var2":0,"var3":0},{"perk":8242,"var1":34,"var2":0,"var3":0}],"style":8400}]},"totalMinionsKilled":142,"win":true},{"summonerName":"Tar2an","kills":12,"assists":8,"deaths":1,"champLevel":14,"championName":"Nidalee","detectorWardsPlaced":4,"wardsPlaced":10,"wardsKilled":5,"doubleKills":2,"tripleKills":0,"quadreKills":0,"pentaKills":0,"goldEarned":12311,"individualPosition":"JUNGLE","item0":0,"item1":3157,"item2":3020,"item3":1082,"item4":1058,"item5":4636,"item6":3340,"totalDamageDealt":150402,"summoner1Id":11,"summoner2Id":4,"perks":{"statPerks":{"defense":5002,"flex":5008,"offense":5005},"styles":[{"description":"primaryStyle","selections":[{"perk":8128,"var1":1428,"var2":18,"var3":0},{"perk":8143,"var1":424,"var2":0,"var3":0},{"perk":8138,"var1":30,"var2":0,"var3":0},{"perk":8135,"var1":550,"var2":5,"var3":0}],"style":8100},{"description":"subStyle","selections":[{"perk":8210,"var1":2,"var2":0,"var3":0},{"perk":8232,"var1":3,"var2":10,"var3":0}],"style":8200}]},"totalMinionsKilled":33,"win":true},{"summonerName":"KT VicLa","kills":3,"assists":11,"deaths":5,"champLevel":12,"championName":"Sylas","detectorWardsPlaced":2,"wardsPlaced":8,"wardsKilled":2,"doubleKills":0,"tripleKills":0,"quadreKills":0,"pentaKills":0,"goldEarned":7938,"individualPosition":"MIDDLE","item0":0,"item1":3157,"item2":0,"item3":3158,"item4":6656,"item5":1082,"item6":3340,"totalDamageDealt":65051,"summoner1Id":12,"summoner2Id":4,"perks":{"statPerks":{"defense":5003,"flex":5008,"offense":5008},"styles":[{"description":"primaryStyle","selections":[{"perk":8010,"var1":398,"var2":0,"var3":0},{"perk":8009,"var1":1927,"var2":0,"var3":0},{"perk":9105,"var1":11,"var2":10,"var3":0},{"perk":8299,"var1":480,"var2":0,"var3":0}],"style":8000},{"description":"subStyle","selections":[{"perk":8444,"var1":798,"var2":0,"var3":0},{"perk":8242,"var1":50,"var2":0,"var3":0}],"style":8400}]},"totalMinionsKilled":114,"win":true},{"summonerName":"T1 Trigger","kills":13,"assists":6,"deaths":3,"champLevel":13,"championName":"Zeri","detectorWardsPlaced":0,"wardsPlaced":5,"wardsKilled":8,"doubleKills":3,"tripleKills":1,"quadreKills":0,"pentaKills":0,"goldEarned":13579,"individualPosition":"BOTTOM","item0":3031,"item1":6673,"item2":3006,"item3":2055,"item4":3046,"item5":0,"item6":3363,"totalDamageDealt":127486,"summoner1Id":3,"summoner2Id":4,"perks":{"statPerks":{"defense":5002,"flex":5008,"offense":5005},"styles":[{"description":"primaryStyle","selections":[{"perk":8008,"var1":129,"var2":0,"var3":0},{"perk":9111,"var1":927,"var2":380,"var3":0},{"perk":9104,"var1":10,"var2":20,"var3":0},{"perk":8299,"var1":522,"var2":0,"var3":0}],"style":8000},{"description":"subStyle","selections":[{"perk":8139,"var1":718,"var2":0,"var3":0},{"perk":8135,"var1":550,"var2":5,"var3":0}],"style":8100}]},"totalMinionsKilled":188,"win":true},{"summonerName":"독기품기","kills":4,"assists":14,"deaths":3,"champLevel":11,"championName":"Viego","detectorWardsPlaced":6,"wardsPlaced":13,"wardsKilled":6,"doubleKills":0,"tripleKills":0,"quadreKills":0,"pentaKills":0,"goldEarned":7694,"individualPosition":"UTILITY","item0":3143,"item1":2055,"item2":3855,"item3":1029,"item4":3001,"item5":3158,"item6":3364,"totalDamageDealt":28485,"summoner1Id":14,"summoner2Id":4,"perks":{"statPerks":{"defense":5002,"flex":5008,"offense":5005},"styles":[{"description":"primaryStyle","selections":[{"perk":8005,"var1":886,"var2":472,"var3":413},{"perk":9111,"var1":1127,"var2":360,"var3":0},{"perk":9104,"var1":12,"var2":10,"var3":0},{"perk":8014,"var1":305,"var2":0,"var3":0}],"style":8000},{"description":"subStyle","selections":[{"perk":8473,"var1":484,"var2":0,"var3":0},{"perk":8242,"var1":72,"var2":0,"var3":0}],"style":8400}]},"totalMinionsKilled":30,"win":true},{"summonerName":"YuEy","kills":3,"assists":2,"deaths":5,"champLevel":11,"championName":"Sejuani","detectorWardsPlaced":0,"wardsPlaced":6,"wardsKilled":2,"doubleKills":0,"tripleKills":0,"quadreKills":0,"pentaKills":0,"goldEarned":6267,"individualPosition":"TOP","item0":2031,"item1":6662,"item2":1001,"item3":3082,"item4":1054,"item5":3067,"item6":3340,"totalDamageDealt":57867,"summoner1Id":14,"summoner2Id":12,"perks":{"statPerks":{"defense":5001,"flex":5002,"offense":5005},"styles":[{"description":"primaryStyle","selections":[{"perk":8437,"var1":754,"var2":560,"var3":0},{"perk":8446,"var1":692,"var2":0,"var3":0},{"perk":8444,"var1":1005,"var2":0,"var3":0},{"perk":8451,"var1":154,"var2":0,"var3":0}],"style":8400},{"description":"subStyle","selections":[{"perk":8345,"var1":3,"var2":0,"var3":0},{"perk":8347,"var1":0,"var2":0,"var3":0}],"style":8300}]},"totalMinionsKilled":103,"win":false},{"summonerName":"JUGKlNG","kills":1,"assists":7,"deaths":12,"champLevel":10,"championName":"Vi","detectorWardsPlaced":5,"wardsPlaced":7,"wardsKilled":3,"doubleKills":0,"tripleKills":0,"quadreKills":0,"pentaKills":0,"goldEarned":5896,"individualPosition":"JUNGLE","item0":2055,"item1":0,"item2":0,"item3":0,"item4":6632,"item5":2422,"item6":3364,"totalDamageDealt":42469,"summoner1Id":11,"summoner2Id":4,"perks":{"statPerks":{"defense":5002,"flex":5008,"offense":5005},"styles":[{"description":"primaryStyle","selections":[{"perk":8010,"var1":64,"var2":0,"var3":0},{"perk":9111,"var1":290,"var2":160,"var3":0},{"perk":9105,"var1":19,"var2":0,"var3":0},{"perk":8014,"var1":155,"var2":0,"var3":0}],"style":8000},{"description":"subStyle","selections":[{"perk":8304,"var1":9,"var2":4,"var3":5},{"perk":8347,"var1":0,"var2":0,"var3":0}],"style":8300}]},"totalMinionsKilled":23,"win":false},{"summonerName":"움싸 닭","kills":2,"assists":5,"deaths":6,"champLevel":12,"championName":"Azir","detectorWardsPlaced":1,"wardsPlaced":5,"wardsKilled":2,"doubleKills":0,"tripleKills":0,"quadreKills":0,"pentaKills":0,"goldEarned":6539,"individualPosition":"MIDDLE","item0":2031,"item1":4644,"item2":3145,"item3":1056,"item4":0,"item5":1001,"item6":3363,"totalDamageDealt":68499,"summoner1Id":14,"summoner2Id":4,"perks":{"statPerks":{"defense":5003,"flex":5008,"offense":5005},"styles":[{"description":"primaryStyle","selections":[{"perk":8010,"var1":145,"var2":0,"var3":0},{"perk":8009,"var1":1930,"var2":0,"var3":0},{"perk":9104,"var1":19,"var2":0,"var3":0},{"perk":8014,"var1":115,"var2":0,"var3":0}],"style":8000},{"description":"subStyle","selections":[{"perk":8226,"var1":250,"var2":576,"var3":0},{"perk":8210,"var1":4,"var2":0,"var3":0}],"style":8200}]},"totalMinionsKilled":132,"win":false},{"summonerName":"4006114","kills":3,"assists":4,"deaths":7,"champLevel":11,"championName":"Yasuo","detectorWardsPlaced":1,"wardsPlaced":6,"wardsKilled":5,"doubleKills":0,"tripleKills":0,"quadreKills":0,"pentaKills":0,"goldEarned":6652,"individualPosition":"BOTTOM","item0":6673,"item1":2031,"item2":3006,"item3":0,"item4":0,"item5":0,"item6":3340,"totalDamageDealt":48980,"summoner1Id":4,"summoner2Id":3,"perks":{"statPerks":{"defense":5002,"flex":5008,"offense":5005},"styles":[{"description":"primaryStyle","selections":[{"perk":8008,"var1":15,"var2":2,"var3":0},{"perk":9111,"var1":465,"var2":140,"var3":0},{"perk":9104,"var1":19,"var2":10,"var3":0},{"perk":8299,"var1":364,"var2":0,"var3":0}],"style":8000},{"description":"subStyle","selections":[{"perk":8444,"var1":545,"var2":0,"var3":0},{"perk":8242,"var1":76,"var2":0,"var3":0}],"style":8400}]},"totalMinionsKilled":115,"win":false},{"summonerName":"Gen G Akia","kills":4,"assists":1,"deaths":8,"champLevel":9,"championName":"Pyke","detectorWardsPlaced":4,"wardsPlaced":22,"wardsKilled":4,"doubleKills":1,"tripleKills":0,"quadreKills":0,"pentaKills":0,"goldEarned":5689,"individualPosition":"UTILITY","item0":3179,"item1":2055,"item2":3855,"item3":3117,"item4":3134,"item5":0,"item6":3364,"totalDamageDealt":15814,"summoner1Id":14,"summoner2Id":4,"perks":{"statPerks":{"defense":5002,"flex":5008,"offense":5008},"styles":[{"description":"primaryStyle","selections":[{"perk":9923,"var1":18,"var2":54,"var3":0},{"perk":8126,"var1":214,"var2":0,"var3":0},{"perk":8136,"var1":6,"var2":12,"var3":0},{"perk":8135,"var1":270,"var2":3,"var3":0}],"style":8100},{"description":"subStyle","selections":[{"perk":8316,"var1":114,"var2":0,"var3":0},{"perk":8347,"var1":0,"var2":0,"var3":0}],"style":8300}]},"totalMinionsKilled":21,"win":false}]},{"summonerName":"JUGKlNG","gameStartTimestamp":1659546522086,"gameEndTimestamp":1659547437747,"gameId":6055702955,"gameDuration":915,"gameMode":"CLASSIC","totalKills":13,"participants":[{"summonerName":"간절남자","kills":0,"assists":1,"deaths":3,"champLevel":10,"championName":"Gwen","detectorWardsPlaced":1,"wardsPlaced":6,"wardsKilled":1,"doubleKills":0,"tripleKills":0,"quadreKills":0,"pentaKills":0,"goldEarned":4775,"individualPosition":"TOP","item0":3047,"item1":2010,"item2":2031,"item3":1056,"item4":1026,"item5":4635,"item6":3340,"totalDamageDealt":77057,"summoner1Id":14,"summoner2Id":12,"perks":{"statPerks":{"defense":5002,"flex":5008,"offense":5005},"styles":[{"description":"primaryStyle","selections":[{"perk":8010,"var1":107,"var2":0,"var3":0},{"perk":8009,"var1":428,"var2":0,"var3":0},{"perk":9104,"var1":0,"var2":0,"var3":0},{"perk":8299,"var1":101,"var2":0,"var3":0}],"style":8000},{"description":"subStyle","selections":[{"perk":8345,"var1":3,"var2":0,"var3":0},{"perk":8347,"var1":0,"var2":0,"var3":0}],"style":8300}]},"totalMinionsKilled":121,"win":true},{"summonerName":"JUGKlNG","kills":5,"assists":7,"deaths":0,"champLevel":10,"championName":"MonkeyKing","detectorWardsPlaced":3,"wardsPlaced":4,"wardsKilled":4,"doubleKills":1,"tripleKills":0,"quadreKills":0,"pentaKills":0,"goldEarned":7004,"individualPosition":"JUNGLE","item0":0,"item1":2031,"item2":0,"item3":3133,"item4":6632,"item5":3047,"item6":3364,"totalDamageDealt":64105,"summoner1Id":11,"summoner2Id":4,"perks":{"statPerks":{"defense":5001,"flex":5008,"offense":5005},"styles":[{"description":"primaryStyle","selections":[{"perk":8010,"var1":227,"var2":0,"var3":0},{"perk":9111,"var1":618,"var2":240,"var3":0},{"perk":9105,"var1":11,"var2":30,"var3":0},{"perk":8014,"var1":225,"var2":0,"var3":0}],"style":8000},{"description":"subStyle","selections":[{"perk":8304,"var1":9,"var2":0,"var3":0},{"perk":8347,"var1":0,"var2":0,"var3":0}],"style":8300}]},"totalMinionsKilled":10,"win":true},{"summonerName":"KT VicLa","kills":1,"assists":3,"deaths":0,"champLevel":12,"championName":"Ryze","detectorWardsPlaced":2,"wardsPlaced":4,"wardsKilled":1,"doubleKills":0,"tripleKills":0,"quadreKills":0,"pentaKills":0,"goldEarned":6267,"individualPosition":"MIDDLE","item0":0,"item1":2423,"item2":2033,"item3":3020,"item4":4644,"item5":3070,"item6":3364,"totalDamageDealt":71435,"summoner1Id":12,"summoner2Id":4,"perks":{"statPerks":{"defense":5003,"flex":5008,"offense":5005},"styles":[{"description":"primaryStyle","selections":[{"perk":8360,"var1":4,"var2":0,"var3":0},{"perk":8313,"var1":0,"var2":0,"var3":0},{"perk":8345,"var1":3,"var2":0,"var3":0},{"perk":8352,"var1":175,"var2":469,"var3":369}],"style":8300},{"description":"subStyle","selections":[{"perk":8226,"var1":250,"var2":836,"var3":0},{"perk":8234,"var1":3813,"var2":0,"var3":0}],"style":8200}]},"totalMinionsKilled":163,"win":true},{"summonerName":"pleatazz","kills":7,"assists":4,"deaths":1,"champLevel":10,"championName":"Zeri","detectorWardsPlaced":1,"wardsPlaced":5,"wardsKilled":6,"doubleKills":2,"tripleKills":1,"quadreKills":1,"pentaKills":0,"goldEarned":9168,"individualPosition":"BOTTOM","item0":6673,"item1":2031,"item2":0,"item3":3086,"item4":1036,"item5":3006,"item6":3340,"totalDamageDealt":56282,"summoner1Id":6,"summoner2Id":4,"perks":{"statPerks":{"defense":5002,"flex":5008,"offense":5005},"styles":[{"description":"primaryStyle","selections":[{"perk":8008,"var1":49,"var2":0,"var3":0},{"perk":9111,"var1":632,"var2":220,"var3":0},{"perk":9104,"var1":12,"var2":30,"var3":0},{"perk":8014,"var1":249,"var2":0,"var3":0}],"style":8000},{"description":"subStyle","selections":[{"perk":8139,"var1":251,"var2":0,"var3":0},{"perk":8135,"var1":550,"var2":5,"var3":0}],"style":8100}]},"totalMinionsKilled":128,"win":true},{"summonerName":"갈과 배 음료","kills":0,"assists":6,"deaths":3,"champLevel":8,"championName":"Sett","detectorWardsPlaced":4,"wardsPlaced":9,"wardsKilled":4,"doubleKills":0,"tripleKills":0,"quadreKills":0,"pentaKills":0,"goldEarned":3383,"individualPosition":"UTILITY","item0":3855,"item1":2031,"item2":2055,"item3":3009,"item4":3066,"item5":1028,"item6":3364,"totalDamageDealt":13482,"summoner1Id":14,"summoner2Id":4,"perks":{"statPerks":{"defense":5002,"flex":5008,"offense":5008},"styles":[{"description":"primaryStyle","selections":[{"perk":8351,"var1":10,"var2":27,"var3":0},{"perk":8306,"var1":1,"var2":0,"var3":0},{"perk":8321,"var1":1,"var2":0,"var3":0},{"perk":8410,"var1":24,"var2":0,"var3":0}],"style":8300},{"description":"subStyle","selections":[{"perk":8275,"var1":5,"var2":0,"var3":0},{"perk":8234,"var1":5004,"var2":0,"var3":0}],"style":8200}]},"totalMinionsKilled":23,"win":true},{"summonerName":"V5ppg0d","kills":0,"assists":3,"deaths":2,"champLevel":10,"championName":"Aatrox","detectorWardsPlaced":1,"wardsPlaced":7,"wardsKilled":1,"doubleKills":0,"tripleKills":0,"quadreKills":0,"pentaKills":0,"goldEarned":5315,"individualPosition":"TOP","item0":6692,"item1":3158,"item2":1033,"item3":1054,"item4":0,"item5":0,"item6":3340,"totalDamageDealt":45331,"summoner1Id":4,"summoner2Id":12,"perks":{"statPerks":{"defense":5002,"flex":5008,"offense":5008},"styles":[{"description":"primaryStyle","selections":[{"perk":8010,"var1":17,"var2":0,"var3":0},{"perk":9111,"var1":109,"var2":60,"var3":0},{"perk":9104,"var1":0,"var2":0,"var3":0},{"perk":8299,"var1":161,"var2":0,"var3":0}],"style":8000},{"description":"subStyle","selections":[{"perk":8143,"var1":98,"var2":0,"var3":0},{"perk":8134,"var1":15,"var2":1,"var3":0}],"style":8100}]},"totalMinionsKilled":107,"win":false},{"summonerName":"어디간거니","kills":3,"assists":2,"deaths":1,"champLevel":10,"championName":"Pantheon","detectorWardsPlaced":1,"wardsPlaced":3,"wardsKilled":2,"doubleKills":0,"tripleKills":0,"quadreKills":0,"pentaKills":0,"goldEarned":6411,"individualPosition":"JUNGLE","item0":6630,"item1":3158,"item2":1036,"item3":3155,"item4":0,"item5":0,"item6":3364,"totalDamageDealt":88684,"summoner1Id":4,"summoner2Id":11,"perks":{"statPerks":{"defense":5002,"flex":5008,"offense":5005},"styles":[{"description":"primaryStyle","selections":[{"perk":8010,"var1":31,"var2":0,"var3":0},{"perk":9111,"var1":58,"var2":100,"var3":0},{"perk":9104,"var1":12,"var2":10,"var3":0},{"perk":8299,"var1":52,"var2":0,"var3":0}],"style":8000},{"description":"subStyle","selections":[{"perk":8304,"var1":10,"var2":3,"var3":0},{"perk":8347,"var1":0,"var2":0,"var3":0}],"style":8300}]},"totalMinionsKilled":11,"win":false},{"summonerName":"Radiohead","kills":0,"assists":3,"deaths":2,"champLevel":10,"championName":"Sylas","detectorWardsPlaced":2,"wardsPlaced":5,"wardsKilled":0,"doubleKills":0,"tripleKills":0,"quadreKills":0,"pentaKills":0,"goldEarned":4587,"individualPosition":"MIDDLE","item0":2031,"item1":2055,"item2":3067,"item3":3802,"item4":1054,"item5":3158,"item6":3364,"totalDamageDealt":40281,"summoner1Id":12,"summoner2Id":4,"perks":{"statPerks":{"defense":5003,"flex":5008,"offense":5007},"styles":[{"description":"primaryStyle","selections":[{"perk":8010,"var1":58,"var2":0,"var3":0},{"perk":8009,"var1":502,"var2":0,"var3":0},{"perk":9105,"var1":0,"var2":0,"var3":0},{"perk":8299,"var1":142,"var2":0,"var3":0}],"style":8000},{"description":"subStyle","selections":[{"perk":8473,"var1":395,"var2":0,"var3":0},{"perk":8242,"var1":23,"var2":0,"var3":0}],"style":8400}]},"totalMinionsKilled":112,"win":false},{"summonerName":"T1 Trigger","kills":3,"assists":2,"deaths":4,"champLevel":9,"championName":"Sivir","detectorWardsPlaced":3,"wardsPlaced":7,"wardsKilled":2,"doubleKills":1,"tripleKills":0,"quadreKills":0,"pentaKills":0,"goldEarned":6316,"individualPosition":"BOTTOM","item0":1083,"item1":6672,"item2":3006,"item3":3086,"item4":0,"item5":0,"item6":3363,"totalDamageDealt":60156,"summoner1Id":7,"summoner2Id":4,"perks":{"statPerks":{"defense":5002,"flex":5008,"offense":5005},"styles":[{"description":"primaryStyle","selections":[{"perk":8008,"var1":15,"var2":1,"var3":0},{"perk":8009,"var1":642,"var2":0,"var3":0},{"perk":9103,"var1":0,"var2":0,"var3":0},{"perk":8017,"var1":325,"var2":0,"var3":0}],"style":8000},{"description":"subStyle","selections":[{"perk":8304,"var1":9,"var2":4,"var3":5},{"perk":8345,"var1":3,"var2":0,"var3":0}],"style":8300}]},"totalMinionsKilled":114,"win":false},{"summonerName":"zkzb","kills":1,"assists":4,"deaths":4,"champLevel":7,"championName":"Yuumi","detectorWardsPlaced":3,"wardsPlaced":12,"wardsKilled":3,"doubleKills":0,"tripleKills":0,"quadreKills":0,"pentaKills":0,"goldEarned":4090,"individualPosition":"UTILITY","item0":3851,"item1":0,"item2":0,"item3":6617,"item4":0,"item5":0,"item6":3364,"totalDamageDealt":5620,"summoner1Id":3,"summoner2Id":14,"perks":{"statPerks":{"defense":5002,"flex":5008,"offense":5008},"styles":[{"description":"primaryStyle","selections":[{"perk":8214,"var1":374,"var2":287,"var3":0},{"perk":8226,"var1":250,"var2":93,"var3":0},{"perk":8210,"var1":0,"var2":0,"var3":0},{"perk":8237,"var1":279,"var2":0,"var3":0}],"style":8200},{"description":"subStyle","selections":[{"perk":8009,"var1":750,"var2":0,"var3":0},{"perk":8017,"var1":105,"var2":0,"var3":0}],"style":8000}]},"totalMinionsKilled":4,"win":false}]},{"summonerName":"JUGKlNG","gameStartTimestamp":1659544981622,"gameEndTimestamp":1659545914985,"gameId":6055660528,"gameDuration":933,"gameMode":"CLASSIC","totalKills":9,"participants":[{"summonerName":"JUGKlNG","kills":3,"assists":1,"deaths":5,"champLevel":9,"championName":"Akshan","detectorWardsPlaced":2,"wardsPlaced":8,"wardsKilled":1,"doubleKills":0,"tripleKills":0,"quadreKills":0,"pentaKills":0,"goldEarned":5824,"individualPosition":"TOP","item0":6671,"item1":2055,"item2":0,"item3":0,"item4":1018,"item5":3020,"item6":3363,"totalDamageDealt":43448,"summoner1Id":14,"summoner2Id":4,"perks":{"statPerks":{"defense":5003,"flex":5008,"offense":5005},"styles":[{"description":"primaryStyle","selections":[{"perk":8021,"var1":1052,"var2":777,"var3":0},{"perk":8009,"var1":611,"var2":0,"var3":0},{"perk":9104,"var1":0,"var2":0,"var3":0},{"perk":8014,"var1":177,"var2":0,"var3":0}],"style":8000},{"description":"subStyle","selections":[{"perk":8143,"var1":155,"var2":0,"var3":0},{"perk":8134,"var1":15,"var2":3,"var3":0}],"style":8100}]},"totalMinionsKilled":99,"win":false},{"summonerName":"이끌어가는자","kills":2,"assists":3,"deaths":3,"champLevel":9,"championName":"Taliyah","detectorWardsPlaced":2,"wardsPlaced":8,"wardsKilled":3,"doubleKills":0,"tripleKills":0,"quadreKills":0,"pentaKills":0,"goldEarned":5492,"individualPosition":"JUNGLE","item0":6655,"item1":1052,"item2":0,"item3":0,"item4":0,"item5":3020,"item6":3364,"totalDamageDealt":58203,"summoner1Id":11,"summoner2Id":4,"perks":{"statPerks":{"defense":5002,"flex":5008,"offense":5005},"styles":[{"description":"primaryStyle","selections":[{"perk":8369,"var1":359,"var2":306,"var3":0},{"perk":8304,"var1":9,"var2":4,"var3":5},{"perk":8321,"var1":2,"var2":0,"var3":0},{"perk":8347,"var1":0,"var2":0,"var3":0}],"style":8300},{"description":"subStyle","selections":[{"perk":8136,"var1":4,"var2":8,"var3":0},{"perk":8135,"var1":270,"var2":3,"var3":0}],"style":8100}]},"totalMinionsKilled":11,"win":false},{"summonerName":"gannijma","kills":1,"assists":4,"deaths":5,"champLevel":10,"championName":"Yone","detectorWardsPlaced":0,"wardsPlaced":4,"wardsKilled":0,"doubleKills":0,"tripleKills":0,"quadreKills":0,"pentaKills":0,"goldEarned":5436,"individualPosition":"MIDDLE","item0":2031,"item1":2055,"item2":0,"item3":3006,"item4":3153,"item5":1054,"item6":3364,"totalDamageDealt":41253,"summoner1Id":4,"summoner2Id":12,"perks":{"statPerks":{"defense":5003,"flex":5008,"offense":5005},"styles":[{"description":"primaryStyle","selections":[{"perk":8008,"var1":19,"var2":1,"var3":0},{"perk":9111,"var1":118,"var2":100,"var3":0},{"perk":9104,"var1":0,"var2":0,"var3":0},{"perk":8299,"var1":202,"var2":0,"var3":0}],"style":8000},{"description":"subStyle","selections":[{"perk":8444,"var1":919,"var2":0,"var3":0},{"perk":8451,"var1":110,"var2":0,"var3":0}],"style":8400}]},"totalMinionsKilled":90,"win":false},{"summonerName":"Happie","kills":3,"assists":1,"deaths":4,"champLevel":9,"championName":"Ezreal","detectorWardsPlaced":1,"wardsPlaced":3,"wardsKilled":1,"doubleKills":1,"tripleKills":0,"quadreKills":0,"pentaKills":0,"goldEarned":5642,"individualPosition":"BOTTOM","item0":2422,"item1":3004,"item2":2031,"item3":1055,"item4":3057,"item5":3051,"item6":3340,"totalDamageDealt":37026,"summoner1Id":4,"summoner2Id":7,"perks":{"statPerks":{"defense":5002,"flex":5008,"offense":5005},"styles":[{"description":"primaryStyle","selections":[{"perk":8369,"var1":324,"var2":242,"var3":0},{"perk":8304,"var1":10,"var2":3,"var3":0},{"perk":8345,"var1":3,"var2":0,"var3":0},{"perk":8347,"var1":0,"var2":0,"var3":0}],"style":8300},{"description":"subStyle","selections":[{"perk":8226,"var1":250,"var2":335,"var3":0},{"perk":8210,"var1":0,"var2":0,"var3":0}],"style":8200}]},"totalMinionsKilled":104,"win":false},{"summonerName":"psavncav","kills":0,"assists":5,"deaths":5,"champLevel":7,"championName":"Braum","detectorWardsPlaced":3,"wardsPlaced":14,"wardsKilled":2,"doubleKills":0,"tripleKills":0,"quadreKills":0,"pentaKills":0,"goldEarned":3637,"individualPosition":"UTILITY","item0":1033,"item1":3859,"item2":0,"item3":3067,"item4":3047,"item5":2031,"item6":3364,"totalDamageDealt":14688,"summoner1Id":4,"summoner2Id":3,"perks":{"statPerks":{"defense":5002,"flex":5002,"offense":5005},"styles":[{"description":"primaryStyle","selections":[{"perk":8465,"var1":522,"var2":0,"var3":0},{"perk":8463,"var1":733,"var2":0,"var3":0},{"perk":8473,"var1":272,"var2":0,"var3":0},{"perk":8242,"var1":45,"var2":0,"var3":0}],"style":8400},{"description":"subStyle","selections":[{"perk":8316,"var1":151,"var2":0,"var3":0},{"perk":8313,"var1":0,"var2":0,"var3":0}],"style":8300}]},"totalMinionsKilled":24,"win":false},{"summonerName":"베란다캥거루","kills":5,"assists":7,"deaths":1,"champLevel":11,"championName":"Galio","detectorWardsPlaced":0,"wardsPlaced":3,"wardsKilled":1,"doubleKills":0,"tripleKills":0,"quadreKills":0,"pentaKills":0,"goldEarned":5984,"individualPosition":"TOP","item0":6664,"item1":3158,"item2":3024,"item3":3082,"item4":0,"item5":0,"item6":3364,"totalDamageDealt":45010,"summoner1Id":6,"summoner2Id":12,"perks":{"statPerks":{"defense":5001,"flex":5002,"offense":5008},"styles":[{"description":"primaryStyle","selections":[{"perk":8230,"var1":10,"var2":0,"var3":0},{"perk":8226,"var1":250,"var2":214,"var3":0},{"perk":8210,"var1":0,"var2":0,"var3":0},{"perk":8236,"var1":8,"var2":0,"var3":0}],"style":8200},{"description":"subStyle","selections":[{"perk":8429,"var1":22,"var2":13,"var3":11},{"perk":8451,"var1":138,"var2":0,"var3":0}],"style":8400}]},"totalMinionsKilled":84,"win":true},{"summonerName":"어디간거니","kills":7,"assists":4,"deaths":2,"champLevel":11,"championName":"Talon","detectorWardsPlaced":1,"wardsPlaced":3,"wardsKilled":3,"doubleKills":0,"tripleKills":0,"quadreKills":0,"pentaKills":0,"goldEarned":8535,"individualPosition":"JUNGLE","item0":6692,"item1":3158,"item2":3142,"item3":0,"item4":0,"item5":0,"item6":3364,"totalDamageDealt":88599,"summoner1Id":4,"summoner2Id":11,"perks":{"statPerks":{"defense":5001,"flex":5008,"offense":5008},"styles":[{"description":"primaryStyle","selections":[{"perk":8369,"var1":505,"var2":439,"var3":0},{"perk":8304,"var1":9,"var2":4,"var3":5},{"perk":8321,"var1":2,"var2":0,"var3":0},{"perk":8347,"var1":0,"var2":0,"var3":0}],"style":8300},{"description":"subStyle","selections":[{"perk":8143,"var1":390,"var2":0,"var3":0},{"perk":8135,"var1":550,"var2":5,"var3":0}],"style":8100}]},"totalMinionsKilled":20,"win":true},{"summonerName":"KT VicLa","kills":3,"assists":2,"deaths":3,"champLevel":10,"championName":"Azir","detectorWardsPlaced":3,"wardsPlaced":7,"wardsKilled":3,"doubleKills":0,"tripleKills":0,"quadreKills":0,"pentaKills":0,"goldEarned":6018,"individualPosition":"MIDDLE","item0":1052,"item1":4644,"item2":2031,"item3":1056,"item4":1028,"item5":3020,"item6":3364,"totalDamageDealt":48082,"summoner1Id":12,"summoner2Id":4,"perks":{"statPerks":{"defense":5003,"flex":5008,"offense":5005},"styles":[{"description":"primaryStyle","selections":[{"perk":8010,"var1":50,"var2":0,"var3":0},{"perk":8009,"var1":1009,"var2":0,"var3":0},{"perk":9104,"var1":0,"var2":0,"var3":0},{"perk":8014,"var1":217,"var2":0,"var3":0}],"style":8000},{"description":"subStyle","selections":[{"perk":8345,"var1":3,"var2":0,"var3":0},{"perk":8347,"var1":0,"var2":0,"var3":0}],"style":8300}]},"totalMinionsKilled":111,"win":true},{"summonerName":"CCwhitte","kills":6,"assists":1,"deaths":1,"champLevel":10,"championName":"Draven","detectorWardsPlaced":0,"wardsPlaced":5,"wardsKilled":0,"doubleKills":1,"tripleKills":0,"quadreKills":0,"pentaKills":0,"goldEarned":10079,"individualPosition":"BOTTOM","item0":1055,"item1":3508,"item2":6692,"item3":3006,"item4":3094,"item5":2055,"item6":3363,"totalDamageDealt":66296,"summoner1Id":1,"summoner2Id":4,"perks":{"statPerks":{"defense":5002,"flex":5008,"offense":5005},"styles":[{"description":"primaryStyle","selections":[{"perk":8008,"var1":30,"var2":4,"var3":0},{"perk":8009,"var1":785,"var2":0,"var3":0},{"perk":9103,"var1":0,"var2":0,"var3":0},{"perk":8014,"var1":240,"var2":0,"var3":0}],"style":8000},{"description":"subStyle","selections":[{"perk":8139,"var1":378,"var2":0,"var3":0},{"perk":8135,"var1":550,"var2":5,"var3":0}],"style":8100}]},"totalMinionsKilled":126,"win":true},{"summonerName":"PIG 1vs5 LOOK","kills":1,"assists":9,"deaths":2,"champLevel":8,"championName":"Nautilus","detectorWardsPlaced":3,"wardsPlaced":12,"wardsKilled":2,"doubleKills":0,"tripleKills":0,"quadreKills":0,"pentaKills":0,"goldEarned":4287,"individualPosition":"UTILITY","item0":3859,"item1":2055,"item2":0,"item3":3105,"item4":3067,"item5":3111,"item6":3364,"totalDamageDealt":12839,"summoner1Id":14,"summoner2Id":4,"perks":{"statPerks":{"defense":5002,"flex":5003,"offense":5005},"styles":[{"description":"primaryStyle","selections":[{"perk":8351,"var1":32,"var2":171,"var3":0},{"perk":8306,"var1":1,"var2":0,"var3":0},{"perk":8316,"var1":316,"var2":0,"var3":0},{"perk":8347,"var1":0,"var2":0,"var3":0}],"style":8300},{"description":"subStyle","selections":[{"perk":8242,"var1":34,"var2":0,"var3":0},{"perk":8444,"var1":473,"var2":0,"var3":0}],"style":8400}]},"totalMinionsKilled":23,"win":true}]},{"summonerName":"JUGKlNG","gameStartTimestamp":1659543082668,"gameEndTimestamp":1659544269166,"gameId":6055366378,"gameDuration":1186,"gameMode":"CLASSIC","totalKills":10,"participants":[{"summonerName":"나를 다시 일으켜","kills":2,"assists":4,"deaths":3,"champLevel":12,"championName":"Lillia","detectorWardsPlaced":2,"wardsPlaced":8,"wardsKilled":2,"doubleKills":0,"tripleKills":0,"quadreKills":0,"pentaKills":0,"goldEarned":8452,"individualPosition":"TOP","item0":3116,"item1":4632,"item2":0,"item3":4644,"item4":1056,"item5":3158,"item6":3364,"totalDamageDealt":110941,"summoner1Id":12,"summoner2Id":4,"perks":{"statPerks":{"defense":5003,"flex":5008,"offense":5008},"styles":[{"description":"primaryStyle","selections":[{"perk":8010,"var1":131,"var2":0,"var3":0},{"perk":8009,"var1":1773,"var2":0,"var3":0},{"perk":9105,"var1":18,"var2":10,"var3":0},{"perk":8299,"var1":334,"var2":0,"var3":0}],"style":8000},{"description":"subStyle","selections":[{"perk":8473,"var1":293,"var2":0,"var3":0},{"perk":8242,"var1":59,"var2":0,"var3":0}],"style":8400}]},"totalMinionsKilled":172,"win":false},{"summonerName":"GJGJGJGJG","kills":2,"assists":4,"deaths":5,"champLevel":11,"championName":"Belveth","detectorWardsPlaced":3,"wardsPlaced":5,"wardsKilled":3,"doubleKills":0,"tripleKills":0,"quadreKills":0,"pentaKills":0,"goldEarned":6704,"individualPosition":"JUNGLE","item0":3153,"item1":6660,"item2":3111,"item3":1033,"item4":0,"item5":0,"item6":3364,"totalDamageDealt":80319,"summoner1Id":11,"summoner2Id":4,"perks":{"statPerks":{"defense":5002,"flex":5008,"offense":5005},"styles":[{"description":"primaryStyle","selections":[{"perk":8010,"var1":180,"var2":0,"var3":0},{"perk":9111,"var1":297,"var2":120,"var3":0},{"perk":9105,"var1":18,"var2":20,"var3":0},{"perk":8014,"var1":129,"var2":0,"var3":0}],"style":8000},{"description":"subStyle","selections":[{"perk":8304,"var1":9,"var2":4,"var3":5},{"perk":8347,"var1":0,"var2":0,"var3":0}],"style":8300}]},"totalMinionsKilled":18,"win":false},{"summonerName":"cikcik","kills":1,"assists":0,"deaths":8,"champLevel":11,"championName":"Sylas","detectorWardsPlaced":1,"wardsPlaced":4,"wardsKilled":1,"doubleKills":0,"tripleKills":0,"quadreKills":0,"pentaKills":0,"goldEarned":6023,"individualPosition":"MIDDLE","item0":2055,"item1":3158,"item2":2031,"item3":6656,"item4":1054,"item5":1056,"item6":3364,"totalDamageDealt":55845,"summoner1Id":12,"summoner2Id":4,"perks":{"statPerks":{"defense":5003,"flex":5008,"offense":5007},"styles":[{"description":"primaryStyle","selections":[{"perk":8010,"var1":51,"var2":0,"var3":0},{"perk":8009,"var1":279,"var2":0,"var3":0},{"perk":9105,"var1":0,"var2":0,"var3":0},{"perk":8299,"var1":283,"var2":0,"var3":0}],"style":8000},{"description":"subStyle","selections":[{"perk":8444,"var1":681,"var2":0,"var3":0},{"perk":8242,"var1":69,"var2":0,"var3":0}],"style":8400}]},"totalMinionsKilled":115,"win":false},{"summonerName":"격투맨 구마유시3","kills":3,"assists":3,"deaths":5,"champLevel":11,"championName":"Ezreal","detectorWardsPlaced":0,"wardsPlaced":4,"wardsKilled":3,"doubleKills":0,"tripleKills":0,"quadreKills":0,"pentaKills":0,"goldEarned":8428,"individualPosition":"BOTTOM","item0":3158,"item1":3134,"item2":0,"item3":3508,"item4":3042,"item5":1055,"item6":3363,"totalDamageDealt":75749,"summoner1Id":7,"summoner2Id":4,"perks":{"statPerks":{"defense":5002,"flex":5008,"offense":5005},"styles":[{"description":"primaryStyle","selections":[{"perk":8010,"var1":38,"var2":0,"var3":0},{"perk":8009,"var1":1128,"var2":0,"var3":0},{"perk":9103,"var1":0,"var2":0,"var3":0},{"perk":8014,"var1":206,"var2":0,"var3":0}],"style":8000},{"description":"subStyle","selections":[{"perk":8304,"var1":10,"var2":3,"var3":0},{"perk":8345,"var1":3,"var2":0,"var3":0}],"style":8300}]},"totalMinionsKilled":142,"win":false},{"summonerName":"왁컬로이두","kills":2,"assists":5,"deaths":6,"champLevel":10,"championName":"Senna","detectorWardsPlaced":0,"wardsPlaced":33,"wardsKilled":9,"doubleKills":0,"tripleKills":0,"quadreKills":0,"pentaKills":0,"goldEarned":6587,"individualPosition":"UTILITY","item0":3864,"item1":3134,"item2":3009,"item3":3179,"item4":1053,"item5":1036,"item6":3364,"totalDamageDealt":33726,"summoner1Id":3,"summoner2Id":4,"perks":{"statPerks":{"defense":5002,"flex":5008,"offense":5005},"styles":[{"description":"primaryStyle","selections":[{"perk":8021,"var1":1147,"var2":894,"var3":0},{"perk":8009,"var1":975,"var2":0,"var3":0},{"perk":9104,"var1":0,"var2":0,"var3":0},{"perk":8017,"var1":765,"var2":0,"var3":0}],"style":8000},{"description":"subStyle","selections":[{"perk":8136,"var1":12,"var2":30,"var3":0},{"perk":8135,"var1":400,"var2":4,"var3":0}],"style":8100}]},"totalMinionsKilled":27,"win":false},{"summonerName":"리바이 병장","kills":4,"assists":2,"deaths":3,"champLevel":12,"championName":"Gwen","detectorWardsPlaced":2,"wardsPlaced":6,"wardsKilled":2,"doubleKills":0,"tripleKills":0,"quadreKills":0,"pentaKills":0,"goldEarned":7826,"individualPosition":"TOP","item0":3157,"item1":0,"item2":2031,"item3":3158,"item4":4633,"item5":1056,"item6":3364,"totalDamageDealt":95290,"summoner1Id":6,"summoner2Id":12,"perks":{"statPerks":{"defense":5003,"flex":5008,"offense":5005},"styles":[{"description":"primaryStyle","selections":[{"perk":8010,"var1":226,"var2":0,"var3":0},{"perk":8009,"var1":1133,"var2":0,"var3":0},{"perk":9104,"var1":17,"var2":20,"var3":0},{"perk":8299,"var1":542,"var2":0,"var3":0}],"style":8000},{"description":"subStyle","selections":[{"perk":8444,"var1":1019,"var2":0,"var3":0},{"perk":8242,"var1":60,"var2":0,"var3":0}],"style":8400}]},"totalMinionsKilled":140,"win":true},{"summonerName":"JUGKlNG","kills":11,"assists":8,"deaths":2,"champLevel":11,"championName":"LeeSin","detectorWardsPlaced":3,"wardsPlaced":10,"wardsKilled":2,"doubleKills":1,"tripleKills":0,"quadreKills":0,"pentaKills":0,"goldEarned":10071,"individualPosition":"JUNGLE","item0":2055,"item1":6693,"item2":3134,"item3":1037,"item4":3814,"item5":3047,"item6":3340,"totalDamageDealt":102042,"summoner1Id":11,"summoner2Id":4,"perks":{"statPerks":{"defense":5001,"flex":5008,"offense":5005},"styles":[{"description":"primaryStyle","selections":[{"perk":8010,"var1":10,"var2":0,"var3":0},{"perk":9111,"var1":1083,"var2":380,"var3":0},{"perk":9105,"var1":8,"var2":0,"var3":0},{"perk":8014,"var1":412,"var2":0,"var3":0}],"style":8000},{"description":"subStyle","selections":[{"perk":8143,"var1":577,"var2":0,"var3":0},{"perk":8134,"var1":24,"var2":5,"var3":0}],"style":8100}]},"totalMinionsKilled":12,"win":true},{"summonerName":"움싸 닭","kills":6,"assists":8,"deaths":1,"champLevel":13,"championName":"Zoe","detectorWardsPlaced":3,"wardsPlaced":7,"wardsKilled":2,"doubleKills":0,"tripleKills":0,"quadreKills":0,"pentaKills":0,"goldEarned":10778,"individualPosition":"MIDDLE","item0":2033,"item1":6655,"item2":3165,"item3":3145,"item4":3041,"item5":3020,"item6":3363,"totalDamageDealt":93181,"summoner1Id":14,"summoner2Id":4,"perks":{"statPerks":{"defense":5003,"flex":5008,"offense":5005},"styles":[{"description":"primaryStyle","selections":[{"perk":8112,"var1":1023,"var2":0,"var3":0},{"perk":8139,"var1":645,"var2":0,"var3":0},{"perk":8138,"var1":30,"var2":0,"var3":0},{"perk":8135,"var1":550,"var2":5,"var3":0}],"style":8100},{"description":"subStyle","selections":[{"perk":8345,"var1":3,"var2":0,"var3":0},{"perk":8352,"var1":262,"var2":686,"var3":560}],"style":8300}]},"totalMinionsKilled":146,"win":true},{"summonerName":"어디간거니","kills":6,"assists":8,"deaths":2,"champLevel":12,"championName":"Sivir","detectorWardsPlaced":2,"wardsPlaced":8,"wardsKilled":3,"doubleKills":0,"tripleKills":0,"quadreKills":0,"pentaKills":0,"goldEarned":10405,"individualPosition":"BOTTOM","item0":6672,"item1":3046,"item2":3026,"item3":1036,"item4":3006,"item5":0,"item6":3363,"totalDamageDealt":119027,"summoner1Id":4,"summoner2Id":7,"perks":{"statPerks":{"defense":5002,"flex":5008,"offense":5005},"styles":[{"description":"primaryStyle","selections":[{"perk":8008,"var1":27,"var2":2,"var3":0},{"perk":8009,"var1":1890,"var2":0,"var3":0},{"perk":9103,"var1":13,"var2":20,"var3":0},{"perk":8014,"var1":377,"var2":0,"var3":0}],"style":8000},{"description":"subStyle","selections":[{"perk":8304,"var1":8,"var2":1,"var3":5},{"perk":8345,"var1":3,"var2":0,"var3":0}],"style":8300}]},"totalMinionsKilled":177,"win":true},{"summonerName":"NS 피터","kills":0,"assists":14,"deaths":2,"champLevel":9,"championName":"Nautilus","detectorWardsPlaced":5,"wardsPlaced":18,"wardsKilled":4,"doubleKills":0,"tripleKills":0,"quadreKills":0,"pentaKills":0,"goldEarned":5741,"individualPosition":"UTILITY","item0":3860,"item1":2420,"item2":3001,"item3":1029,"item4":3009,"item5":2055,"item6":3364,"totalDamageDealt":14297,"summoner1Id":4,"summoner2Id":14,"perks":{"statPerks":{"defense":5002,"flex":5003,"offense":5007},"styles":[{"description":"primaryStyle","selections":[{"perk":8351,"var1":27,"var2":322,"var3":0},{"perk":8306,"var1":2,"var2":0,"var3":0},{"perk":8316,"var1":323,"var2":0,"var3":0},{"perk":8347,"var1":0,"var2":0,"var3":0}],"style":8300},{"description":"subStyle","selections":[{"perk":8444,"var1":529,"var2":0,"var3":0},{"perk":8463,"var1":603,"var2":0,"var3":0}],"style":8400}]},"totalMinionsKilled":25,"win":true}]},{"summonerName":"JUGKlNG","gameStartTimestamp":1659286054684,"gameEndTimestamp":1659287651815,"gameId":6050215839,"gameDuration":1597,"gameMode":"CLASSIC","totalKills":31,"participants":[{"summonerName":"리바이 병장","kills":3,"assists":11,"deaths":3,"champLevel":16,"championName":"LeeSin","detectorWardsPlaced":6,"wardsPlaced":15,"wardsKilled":5,"doubleKills":0,"tripleKills":0,"quadreKills":0,"pentaKills":0,"goldEarned":13128,"individualPosition":"TOP","item0":6630,"item1":3143,"item2":3133,"item3":1028,"item4":3047,"item5":3053,"item6":3340,"totalDamageDealt":181459,"summoner1Id":4,"summoner2Id":12,"perks":{"statPerks":{"defense":5002,"flex":5008,"offense":5008},"styles":[{"description":"primaryStyle","selections":[{"perk":8010,"var1":238,"var2":0,"var3":0},{"perk":9111,"var1":1898,"var2":280,"var3":0},{"perk":9104,"var1":18,"var2":10,"var3":0},{"perk":8299,"var1":641,"var2":0,"var3":0}],"style":8000},{"description":"subStyle","selections":[{"perk":8473,"var1":933,"var2":0,"var3":0},{"perk":8242,"var1":85,"var2":0,"var3":0}],"style":8400}]},"totalMinionsKilled":228,"win":true},{"summonerName":"h941u u ek7","kills":4,"assists":17,"deaths":5,"champLevel":14,"championName":"JarvanIV","detectorWardsPlaced":5,"wardsPlaced":7,"wardsKilled":6,"doubleKills":1,"tripleKills":0,"quadreKills":0,"pentaKills":0,"goldEarned":11075,"individualPosition":"JUNGLE","item0":3067,"item1":2055,"item2":6630,"item3":3071,"item4":3047,"item5":1029,"item6":3364,"totalDamageDealt":138603,"summoner1Id":4,"summoner2Id":11,"perks":{"statPerks":{"defense":5002,"flex":5008,"offense":5005},"styles":[{"description":"primaryStyle","selections":[{"perk":8010,"var1":133,"var2":0,"var3":0},{"perk":9111,"var1":899,"var2":420,"var3":0},{"perk":9105,"var1":12,"var2":0,"var3":0},{"perk":8014,"var1":321,"var2":0,"var3":0}],"style":8000},{"description":"subStyle","selections":[{"perk":8304,"var1":9,"var2":4,"var3":5},{"perk":8347,"var1":0,"var2":0,"var3":0}],"style":8300}]},"totalMinionsKilled":24,"win":true},{"summonerName":"ucal","kills":9,"assists":15,"deaths":2,"champLevel":16,"championName":"Taliyah","detectorWardsPlaced":0,"wardsPlaced":9,"wardsKilled":4,"doubleKills":2,"tripleKills":0,"quadreKills":0,"pentaKills":0,"goldEarned":14351,"individualPosition":"MIDDLE","item0":4645,"item1":3020,"item2":3040,"item3":3116,"item4":1082,"item5":4644,"item6":3363,"totalDamageDealt":161147,"summoner1Id":1,"summoner2Id":4,"perks":{"statPerks":{"defense":5003,"flex":5008,"offense":5005},"styles":[{"description":"primaryStyle","selections":[{"perk":8369,"var1":1246,"var2":792,"var3":0},{"perk":8304,"var1":10,"var2":3,"var3":0},{"perk":8345,"var1":3,"var2":0,"var3":0},{"perk":8347,"var1":0,"var2":0,"var3":0}],"style":8300},{"description":"subStyle","selections":[{"perk":8226,"var1":250,"var2":1426,"var3":0},{"perk":8237,"var1":519,"var2":0,"var3":0}],"style":8200}]},"totalMinionsKilled":210,"win":true},{"summonerName":"deokdam","kills":11,"assists":10,"deaths":1,"champLevel":16,"championName":"Jinx","detectorWardsPlaced":2,"wardsPlaced":10,"wardsKilled":7,"doubleKills":2,"tripleKills":1,"quadreKills":0,"pentaKills":0,"goldEarned":15021,"individualPosition":"BOTTOM","item0":3031,"item1":0,"item2":6672,"item3":1055,"item4":3006,"item5":3094,"item6":3363,"totalDamageDealt":202026,"summoner1Id":4,"summoner2Id":1,"perks":{"statPerks":{"defense":5002,"flex":5008,"offense":5005},"styles":[{"description":"primaryStyle","selections":[{"perk":8008,"var1":82,"var2":12,"var3":0},{"perk":8009,"var1":2884,"var2":0,"var3":0},{"perk":9103,"var1":21,"var2":10,"var3":0},{"perk":8017,"var1":498,"var2":0,"var3":0}],"style":8000},{"description":"subStyle","selections":[{"perk":8345,"var1":3,"var2":0,"var3":0},{"perk":8347,"var1":0,"var2":0,"var3":0}],"style":8300}]},"totalMinionsKilled":217,"win":true},{"summonerName":"zhong men dui ju","kills":4,"assists":14,"deaths":5,"champLevel":12,"championName":"Nautilus","detectorWardsPlaced":9,"wardsPlaced":32,"wardsKilled":12,"doubleKills":0,"tripleKills":0,"quadreKills":0,"pentaKills":0,"goldEarned":7963,"individualPosition":"UTILITY","item0":3860,"item1":0,"item2":3190,"item3":3111,"item4":3067,"item5":1011,"item6":3364,"totalDamageDealt":26561,"summoner1Id":4,"summoner2Id":14,"perks":{"statPerks":{"defense":5003,"flex":5002,"offense":5005},"styles":[{"description":"primaryStyle","selections":[{"perk":8351,"var1":64,"var2":522,"var3":0},{"perk":8306,"var1":2,"var2":0,"var3":0},{"perk":8316,"var1":674,"var2":0,"var3":0},{"perk":8347,"var1":0,"var2":0,"var3":0}],"style":8300},{"description":"subStyle","selections":[{"perk":8473,"var1":703,"var2":0,"var3":0},{"perk":8242,"var1":81,"var2":0,"var3":0}],"style":8400}]},"totalMinionsKilled":39,"win":true},{"summonerName":"갈과 배 음료","kills":1,"assists":2,"deaths":8,"champLevel":13,"championName":"Renekton","detectorWardsPlaced":3,"wardsPlaced":9,"wardsKilled":4,"doubleKills":0,"tripleKills":0,"quadreKills":0,"pentaKills":0,"goldEarned":8148,"individualPosition":"TOP","item0":6664,"item1":0,"item2":1054,"item3":0,"item4":3153,"item5":3047,"item6":3364,"totalDamageDealt":109671,"summoner1Id":12,"summoner2Id":4,"perks":{"statPerks":{"defense":5002,"flex":5008,"offense":5008},"styles":[{"description":"primaryStyle","selections":[{"perk":8005,"var1":1790,"var2":1032,"var3":758},{"perk":9111,"var1":138,"var2":60,"var3":0},{"perk":9105,"var1":0,"var2":0,"var3":0},{"perk":8299,"var1":556,"var2":0,"var3":0}],"style":8000},{"description":"subStyle","selections":[{"perk":8444,"var1":1163,"var2":0,"var3":0},{"perk":8242,"var1":71,"var2":0,"var3":0}],"style":8400}]},"totalMinionsKilled":169,"win":false},{"summonerName":"JUGKlNG","kills":6,"assists":1,"deaths":5,"champLevel":13,"championName":"Pantheon","detectorWardsPlaced":11,"wardsPlaced":13,"wardsKilled":7,"doubleKills":0,"tripleKills":0,"quadreKills":0,"pentaKills":0,"goldEarned":9126,"individualPosition":"JUNGLE","item0":2055,"item1":3142,"item2":1036,"item3":6691,"item4":0,"item5":3047,"item6":3364,"totalDamageDealt":117224,"summoner1Id":11,"summoner2Id":4,"perks":{"statPerks":{"defense":5002,"flex":5008,"offense":5008},"styles":[{"description":"primaryStyle","selections":[{"perk":8010,"var1":160,"var2":0,"var3":0},{"perk":9111,"var1":376,"var2":140,"var3":0},{"perk":9105,"var1":14,"var2":50,"var3":0},{"perk":8014,"var1":316,"var2":0,"var3":0}],"style":8000},{"description":"subStyle","selections":[{"perk":8105,"var1":10,"var2":4,"var3":0},{"perk":8126,"var1":535,"var2":0,"var3":0}],"style":8100}]},"totalMinionsKilled":34,"win":false},{"summonerName":"2345678","kills":4,"assists":4,"deaths":5,"champLevel":14,"championName":"Vex","detectorWardsPlaced":2,"wardsPlaced":11,"wardsKilled":4,"doubleKills":1,"tripleKills":0,"quadreKills":0,"pentaKills":0,"goldEarned":10384,"individualPosition":"MIDDLE","item0":3020,"item1":2421,"item2":6655,"item3":4645,"item4":1052,"item5":1082,"item6":3364,"totalDamageDealt":143871,"summoner1Id":4,"summoner2Id":14,"perks":{"statPerks":{"defense":5003,"flex":5008,"offense":5005},"styles":[{"description":"primaryStyle","selections":[{"perk":8112,"var1":914,"var2":0,"var3":0},{"perk":8139,"var1":544,"var2":0,"var3":0},{"perk":8136,"var1":6,"var2":12,"var3":0},{"perk":8106,"var1":4,"var2":0,"var3":0}],"style":8100},{"description":"subStyle","selections":[{"perk":8233,"var1":18,"var2":20,"var3":0},{"perk":8236,"var1":24,"var2":0,"var3":0}],"style":8200}]},"totalMinionsKilled":217,"win":false},{"summonerName":"qwerdfgzxc","kills":5,"assists":8,"deaths":5,"champLevel":14,"championName":"Sivir","detectorWardsPlaced":2,"wardsPlaced":10,"wardsKilled":9,"doubleKills":1,"tripleKills":0,"quadreKills":0,"pentaKills":0,"goldEarned":11628,"individualPosition":"BOTTOM","item0":2055,"item1":3046,"item2":3036,"item3":3006,"item4":6672,"item5":1055,"item6":3363,"totalDamageDealt":161987,"summoner1Id":4,"summoner2Id":6,"perks":{"statPerks":{"defense":5002,"flex":5008,"offense":5005},"styles":[{"description":"primaryStyle","selections":[{"perk":8008,"var1":95,"var2":9,"var3":0},{"perk":8009,"var1":2069,"var2":0,"var3":0},{"perk":9103,"var1":21,"var2":0,"var3":0},{"perk":8017,"var1":1118,"var2":0,"var3":0}],"style":8000},{"description":"subStyle","selections":[{"perk":8233,"var1":15,"var2":0,"var3":0},{"perk":8236,"var1":14,"var2":0,"var3":0}],"style":8200}]},"totalMinionsKilled":236,"win":false},{"summonerName":"kiwi doctor","kills":0,"assists":11,"deaths":8,"champLevel":11,"championName":"Alistar","detectorWardsPlaced":7,"wardsPlaced":33,"wardsKilled":4,"doubleKills":0,"tripleKills":0,"quadreKills":0,"pentaKills":0,"goldEarned":6073,"individualPosition":"UTILITY","item0":3860,"item1":2055,"item2":2031,"item3":3742,"item4":1028,"item5":3009,"item6":3364,"totalDamageDealt":16445,"summoner1Id":14,"summoner2Id":4,"perks":{"statPerks":{"defense":5002,"flex":5002,"offense":5008},"styles":[{"description":"primaryStyle","selections":[{"perk":8351,"var1":61,"var2":360,"var3":0},{"perk":8306,"var1":4,"var2":0,"var3":0},{"perk":8345,"var1":3,"var2":0,"var3":0},{"perk":8347,"var1":0,"var2":0,"var3":0}],"style":8300},{"description":"subStyle","selections":[{"perk":8473,"var1":508,"var2":0,"var3":0},{"perk":8242,"var1":108,"var2":0,"var3":0}],"style":8400}]},"totalMinionsKilled":27,"win":false}]},{"summonerName":"JUGKlNG","gameStartTimestamp":1659282905266,"gameEndTimestamp":1659285329183,"gameId":6050128778,"gameDuration":2423,"gameMode":"CLASSIC","totalKills":28,"participants":[{"summonerName":"나를 다시 일으켜","kills":5,"assists":8,"deaths":8,"champLevel":17,"championName":"Aatrox","detectorWardsPlaced":1,"wardsPlaced":4,"wardsKilled":12,"doubleKills":0,"tripleKills":0,"quadreKills":0,"pentaKills":0,"goldEarned":14350,"individualPosition":"TOP","item0":3156,"item1":6609,"item2":3026,"item3":1036,"item4":6692,"item5":3158,"item6":3364,"totalDamageDealt":162625,"summoner1Id":12,"summoner2Id":4,"perks":{"statPerks":{"defense":5002,"flex":5008,"offense":5008},"styles":[{"description":"primaryStyle","selections":[{"perk":8010,"var1":39,"var2":0,"var3":0},{"perk":9111,"var1":1015,"var2":260,"var3":0},{"perk":9104,"var1":18,"var2":40,"var3":0},{"perk":8299,"var1":668,"var2":0,"var3":0}],"style":8000},{"description":"subStyle","selections":[{"perk":8451,"var1":230,"var2":0,"var3":0},{"perk":8444,"var1":1784,"var2":0,"var3":0}],"style":8400}]},"totalMinionsKilled":185,"win":false},{"summonerName":"beichuan","kills":3,"assists":13,"deaths":12,"champLevel":16,"championName":"MonkeyKing","detectorWardsPlaced":11,"wardsPlaced":12,"wardsKilled":12,"doubleKills":0,"tripleKills":0,"quadreKills":0,"pentaKills":0,"goldEarned":14108,"individualPosition":"JUNGLE","item0":3143,"item1":6333,"item2":1057,"item3":3066,"item4":6632,"item5":3158,"item6":3364,"totalDamageDealt":202394,"summoner1Id":4,"summoner2Id":11,"perks":{"statPerks":{"defense":5002,"flex":5008,"offense":5005},"styles":[{"description":"primaryStyle","selections":[{"perk":8010,"var1":408,"var2":0,"var3":0},{"perk":9111,"var1":1223,"var2":320,"var3":0},{"perk":9105,"var1":14,"var2":30,"var3":0},{"perk":8014,"var1":419,"var2":0,"var3":0}],"style":8000},{"description":"subStyle","selections":[{"perk":8304,"var1":10,"var2":3,"var3":0},{"perk":8347,"var1":0,"var2":0,"var3":0}],"style":8300}]},"totalMinionsKilled":42,"win":false},{"summonerName":"해가지면달이핀다","kills":6,"assists":10,"deaths":9,"champLevel":18,"championName":"Galio","detectorWardsPlaced":8,"wardsPlaced":11,"wardsKilled":9,"doubleKills":0,"tripleKills":0,"quadreKills":0,"pentaKills":0,"goldEarned":16070,"individualPosition":"MIDDLE","item0":4636,"item1":3157,"item2":4645,"item3":3089,"item4":3108,"item5":3020,"item6":3364,"totalDamageDealt":220784,"summoner1Id":6,"summoner2Id":4,"perks":{"statPerks":{"defense":5003,"flex":5008,"offense":5008},"styles":[{"description":"primaryStyle","selections":[{"perk":8360,"var1":17,"var2":0,"var3":0},{"perk":8304,"var1":9,"var2":4,"var3":5},{"perk":8316,"var1":9371,"var2":0,"var3":0},{"perk":8347,"var1":0,"var2":0,"var3":0}],"style":8300},{"description":"subStyle","selections":[{"perk":8275,"var1":22,"var2":0,"var3":0},{"perk":8234,"var1":15127,"var2":0,"var3":0}],"style":8200}]},"totalMinionsKilled":283,"win":false},{"summonerName":"Hifgsibsap","kills":11,"assists":10,"deaths":7,"champLevel":17,"championName":"Zeri","detectorWardsPlaced":3,"wardsPlaced":16,"wardsKilled":31,"doubleKills":1,"tripleKills":0,"quadreKills":0,"pentaKills":0,"goldEarned":21562,"individualPosition":"BOTTOM","item0":3006,"item1":3091,"item2":3072,"item3":3031,"item4":6673,"item5":3046,"item6":3363,"totalDamageDealt":357932,"summoner1Id":1,"summoner2Id":4,"perks":{"statPerks":{"defense":5002,"flex":5008,"offense":5005},"styles":[{"description":"primaryStyle","selections":[{"perk":8008,"var1":66,"var2":0,"var3":0},{"perk":9111,"var1":911,"var2":420,"var3":0},{"perk":9104,"var1":14,"var2":40,"var3":0},{"perk":8017,"var1":1262,"var2":0,"var3":0}],"style":8000},{"description":"subStyle","selections":[{"perk":8135,"var1":550,"var2":5,"var3":0},{"perk":8139,"var1":1684,"var2":0,"var3":0}],"style":8100}]},"totalMinionsKilled":330,"win":false},{"summonerName":"Rascal","kills":3,"assists":22,"deaths":5,"champLevel":16,"championName":"Yuumi","detectorWardsPlaced":6,"wardsPlaced":59,"wardsKilled":5,"doubleKills":1,"tripleKills":0,"quadreKills":0,"pentaKills":0,"goldEarned":11693,"individualPosition":"UTILITY","item0":3853,"item1":3222,"item2":2421,"item3":6617,"item4":3504,"item5":3011,"item6":3364,"totalDamageDealt":17646,"summoner1Id":14,"summoner2Id":3,"perks":{"statPerks":{"defense":5002,"flex":5008,"offense":5007},"styles":[{"description":"primaryStyle","selections":[{"perk":8214,"var1":2258,"var2":4857,"var3":0},{"perk":8226,"var1":250,"var2":1558,"var3":0},{"perk":8210,"var1":12,"var2":0,"var3":0},{"perk":8236,"var1":80,"var2":0,"var3":0}],"style":8200},{"description":"subStyle","selections":[{"perk":8009,"var1":5118,"var2":0,"var3":0},{"perk":8017,"var1":654,"var2":0,"var3":0}],"style":8000}]},"totalMinionsKilled":11,"win":false},{"summonerName":"JUGKlNG","kills":13,"assists":14,"deaths":8,"champLevel":16,"championName":"Pantheon","detectorWardsPlaced":21,"wardsPlaced":23,"wardsKilled":5,"doubleKills":0,"tripleKills":0,"quadreKills":0,"pentaKills":0,"goldEarned":15390,"individualPosition":"JUNGLE","item0":0,"item1":3142,"item2":2421,"item3":6692,"item4":3071,"item5":3047,"item6":3364,"totalDamageDealt":162556,"summoner1Id":11,"summoner2Id":4,"perks":{"statPerks":{"defense":5002,"flex":5008,"offense":5008},"styles":[{"description":"primaryStyle","selections":[{"perk":8010,"var1":774,"var2":0,"var3":0},{"perk":9111,"var1":1764,"var2":540,"var3":0},{"perk":9105,"var1":8,"var2":30,"var3":0},{"perk":8014,"var1":656,"var2":0,"var3":0}],"style":8000},{"description":"subStyle","selections":[{"perk":8105,"var1":13,"var2":5,"var3":0},{"perk":8126,"var1":1049,"var2":0,"var3":0}],"style":8100}]},"totalMinionsKilled":14,"win":true},{"summonerName":"TPzhao727472857","kills":3,"assists":13,"deaths":8,"champLevel":18,"championName":"Kayle","detectorWardsPlaced":5,"wardsPlaced":17,"wardsKilled":6,"doubleKills":0,"tripleKills":0,"quadreKills":0,"pentaKills":0,"goldEarned":16184,"individualPosition":"TOP","item0":4633,"item1":0,"item2":3006,"item3":3153,"item4":3115,"item5":6694,"item6":3363,"totalDamageDealt":257517,"summoner1Id":4,"summoner2Id":12,"perks":{"statPerks":{"defense":5002,"flex":5008,"offense":5005},"styles":[{"description":"primaryStyle","selections":[{"perk":8008,"var1":78,"var2":8,"var3":0},{"perk":8009,"var1":3401,"var2":0,"var3":0},{"perk":9104,"var1":17,"var2":10,"var3":0},{"perk":8014,"var1":731,"var2":0,"var3":0}],"style":8000},{"description":"subStyle","selections":[{"perk":8473,"var1":735,"var2":0,"var3":0},{"perk":8242,"var1":78,"var2":0,"var3":0}],"style":8400}]},"totalMinionsKilled":291,"win":true},{"summonerName":"HLE Karis1","kills":9,"assists":16,"deaths":3,"champLevel":18,"championName":"Ryze","detectorWardsPlaced":4,"wardsPlaced":7,"wardsKilled":8,"doubleKills":0,"tripleKills":0,"quadreKills":0,"pentaKills":0,"goldEarned":19464,"individualPosition":"MIDDLE","item0":3040,"item1":4644,"item2":4645,"item3":3020,"item4":3089,"item5":3135,"item6":3364,"totalDamageDealt":345748,"summoner1Id":4,"summoner2Id":12,"perks":{"statPerks":{"defense":5003,"flex":5008,"offense":5005},"styles":[{"description":"primaryStyle","selections":[{"perk":8010,"var1":555,"var2":0,"var3":0},{"perk":8009,"var1":7513,"var2":0,"var3":0},{"perk":9105,"var1":10,"var2":40,"var3":0},{"perk":8299,"var1":777,"var2":0,"var3":0}],"style":8000},{"description":"subStyle","selections":[{"perk":8226,"var1":250,"var2":1147,"var3":0},{"perk":8234,"var1":18037,"var2":0,"var3":0}],"style":8200}]},"totalMinionsKilled":325,"win":true},{"summonerName":"대구농민변정현","kills":10,"assists":16,"deaths":4,"champLevel":18,"championName":"Sivir","detectorWardsPlaced":4,"wardsPlaced":16,"wardsKilled":12,"doubleKills":2,"tripleKills":0,"quadreKills":0,"pentaKills":0,"goldEarned":21688,"individualPosition":"BOTTOM","item0":3006,"item1":3036,"item2":3031,"item3":3046,"item4":6672,"item5":3026,"item6":3363,"totalDamageDealt":465725,"summoner1Id":7,"summoner2Id":4,"perks":{"statPerks":{"defense":5002,"flex":5008,"offense":5005},"styles":[{"description":"primaryStyle","selections":[{"perk":8008,"var1":67,"var2":16,"var3":0},{"perk":8009,"var1":4538,"var2":0,"var3":0},{"perk":9103,"var1":16,"var2":20,"var3":0},{"perk":8017,"var1":2166,"var2":0,"var3":0}],"style":8000},{"description":"subStyle","selections":[{"perk":8233,"var1":27,"var2":10,"var3":0},{"perk":8236,"var1":48,"var2":0,"var3":0}],"style":8200}]},"totalMinionsKilled":390,"win":true},{"summonerName":"ioplkmjugwacv","kills":6,"assists":25,"deaths":5,"champLevel":16,"championName":"Karma","detectorWardsPlaced":13,"wardsPlaced":75,"wardsKilled":21,"doubleKills":0,"tripleKills":0,"quadreKills":0,"pentaKills":0,"goldEarned":12391,"individualPosition":"UTILITY","item0":2065,"item1":3853,"item2":0,"item3":3158,"item4":3011,"item5":3504,"item6":3364,"totalDamageDealt":55158,"summoner1Id":14,"summoner2Id":4,"perks":{"statPerks":{"defense":5002,"flex":5008,"offense":5008},"styles":[{"description":"primaryStyle","selections":[{"perk":8229,"var1":2568,"var2":0,"var3":0},{"perk":8275,"var1":16,"var2":0,"var3":0},{"perk":8233,"var1":26,"var2":0,"var3":0},{"perk":8237,"var1":996,"var2":0,"var3":0}],"style":8200},{"description":"subStyle","selections":[{"perk":8345,"var1":3,"var2":0,"var3":0},{"perk":8347,"var1":0,"var2":0,"var3":0}],"style":8300}]},"totalMinionsKilled":34,"win":true}]}]